Workbook

Sheet Sales-Profit by Region
A1: Sales & Profit by Region (Completed Orders Only)
A4: Region | B4: Completed Sales (₹) | C4: Completed Profit (₹) | D4: Profit Margin | E4: Completed Orders
A5: South | B5: =SUMIFS(CleanRef!$T$2:$T$913,CleanRef!$G$2:$G$913,"South",CleanRef!$AH$2:$AH$913,"Yes") -> 1641550 | C5: =SUMIFS(CleanRef!$U$2:$U$913,CleanRef!$G$2:$G$913,"South",CleanRef!$AH$2:$AH$913,"Yes") -> 468067.93 | D5: =IF(B5=0,0,C5/B5) -> 0.28513779 | E5: =COUNTIFS(CleanRef!$G$2:$G$913,"South",CleanRef!$AH$2:$AH$913,"Yes") -> 153
A6: West | B6: =SUMIFS(CleanRef!$T$2:$T$913,CleanRef!$G$2:$G$913,"West",CleanRef!$AH$2:$AH$913,"Yes") -> 1502507.2 | C6: =SUMIFS(CleanRef!$U$2:$U$913,CleanRef!$G$2:$G$913,"West",CleanRef!$AH$2:$AH$913,"Yes") -> 433402.26 | D6: =IF(B6=0,0,C6/B6) -> 0.2884527 | E6: =COUNTIFS(CleanRef!$G$2:$G$913,"West",CleanRef!$AH$2:$AH$913,"Yes") -> 153
A7: East | B7: =SUMIFS(CleanRef!$T$2:$T$913,CleanRef!$G$2:$G$913,"East",CleanRef!$AH$2:$AH$913,"Yes") -> 1385008.4 | C7: =SUMIFS(CleanRef!$U$2:$U$913,CleanRef!$G$2:$G$913,"East",CleanRef!$AH$2:$AH$913,"Yes") -> 418198.97 | D7: =IF(B7=0,0,C7/B7) -> 0.3019469 | E7: =COUNTIFS(CleanRef!$G$2:$G$913,"East",CleanRef!$AH$2:$AH$913,"Yes") -> 149
A8: North | B8: =SUMIFS(CleanRef!$T$2:$T$913,CleanRef!$G$2:$G$913,"North",CleanRef!$AH$2:$AH$913,"Yes") -> 1293210.4 | C8: =SUMIFS(CleanRef!$U$2:$U$913,CleanRef!$G$2:$G$913,"North",CleanRef!$AH$2:$AH$913,"Yes") -> 389626.99 | D8: =IF(B8=0,0,C8/B8) -> 0.30128663 | E8: =COUNTIFS(CleanRef!$G$2:$G$913,"North",CleanRef!$AH$2:$AH$913,"Yes") -> 128
A9: Unknown | B9: =SUMIFS(CleanRef!$T$2:$T$913,CleanRef!$G$2:$G$913,"Unknown",CleanRef!$AH$2:$AH$913,"Yes") -> 187898.46 | C9: =SUMIFS(CleanRef!$U$2:$U$913,CleanRef!$G$2:$G$913,"Unknown",CleanRef!$AH$2:$AH$913,"Yes") -> 63943.192 | D9: =IF(B9=0,0,C9/B9) -> 0.34030716 | E9: =COUNTIFS(CleanRef!$G$2:$G$913,"Unknown",CleanRef!$AH$2:$AH$913,"Yes") -> 19
A10: TOTAL | B10: =SUM(B5:B9) -> 6010174.4 | C10: =SUM(C5:C9) -> 1773239.4 | E10: =SUM(E5:E9) -> 602

Sheet Sales-Profit by Category
A1: Sales & Profit by Category and Sub-Category (Completed Orders Only)
A4: Category | B4: Sub-Category | C4: Completed Sales (₹) | D4: Completed Profit (₹)
A5: Technology | B5: Copiers | C5: =SUMIFS(CleanRef!$T$2:$T$913,CleanRef!$J$2:$J$913,"Technology",CleanRef!$K$2:$K$913,"Copiers",CleanRef!$AH$2:$AH$913,"Yes") -> 670173.31 | D5: =SUMIFS(CleanRef!$U$2:$U$913,CleanRef!$J$2:$J$913,"Technology",CleanRef!$K$2:$K$913,"Copiers",CleanRef!$AH$2:$AH$913,"Yes") -> 194107.97
A6: Technology | B6: Phones | C6: =SUMIFS(CleanRef!$T$2:$T$913,CleanRef!$J$2:$J$913,"Technology",CleanRef!$K$2:$K$913,"Phones",CleanRef!$AH$2:$AH$913,"Yes") -> 585862.47 | D6: =SUMIFS(CleanRef!$U$2:$U$913,CleanRef!$J$2:$J$913,"Technology",CleanRef!$K$2:$K$913,"Phones",CleanRef!$AH$2:$AH$913,"Yes") -> 170370.8
A7: Furniture | B7: Chairs | C7: =SUMIFS(CleanRef!$T$2:$T$913,CleanRef!$J$2:$J$913,"Furniture",CleanRef!$K$2:$K$913,"Chairs",CleanRef!$AH$2:$AH$913,"Yes") -> 583968.65 | D7: =SUMIFS(CleanRef!$U$2:$U$913,CleanRef!$J$2:$J$913,"Furniture",CleanRef!$K$2:$K$913,"Chairs",CleanRef!$AH$2:$AH$913,"Yes") -> 175651.42
A8: Office Supplies | B8: Storage | C8: =SUMIFS(CleanRef!$T$2:$T$913,CleanRef!$J$2:$J$913,"Office Supplies",CleanRef!$K$2:$K$913,"Storage",CleanRef!$AH$2:$AH$913,"Yes") -> 557307.69 | D8: =SUMIFS(CleanRef!$U$2:$U$913,CleanRef!$J$2:$J$913,"Office Supplies",CleanRef!$K$2:$K$913,"Storage",CleanRef!$AH$2:$AH$913,"Yes") -> 150002.36
A9: Technology | B9: Accessories | C9: =SUMIFS(CleanRef!$T$2:$T$913,CleanRef!$J$2:$J$913,"Technology",CleanRef!$K$2:$K$913,"Accessories",CleanRef!$AH$2:$AH$913,"Yes") -> 530334.76 | D9: =SUMIFS(CleanRef!$U$2:$U$913,CleanRef!$J$2:$J$913,"Technology",CleanRef!$K$2:$K$913,"Accessories",CleanRef!$AH$2:$AH$913,"Yes") -> 158243.77
A10: Furniture | B10: Furnishings | C10: =SUMIFS(CleanRef!$T$2:$T$913,CleanRef!$J$2:$J$913,"Furniture",CleanRef!$K$2:$K$913,"Furnishings",CleanRef!$AH$2:$AH$913,"Yes") -> 503021.35 | D10: =SUMIFS(CleanRef!$U$2:$U$913,CleanRef!$J$2:$J$913,"Furniture",CleanRef!$K$2:$K$913,"Furnishings",CleanRef!$AH$2:$AH$913,"Yes") -> 146832.71
A11: Office Supplies | B11: Paper | C11: =SUMIFS(CleanRef!$T$2:$T$913,CleanRef!$J$2:$J$913,"Office Supplies",CleanRef!$K$2:$K$913,"Paper",CleanRef!$AH$2:$AH$913,"Yes") -> 447884.39 | D11: =SUMIFS(CleanRef!$U$2:$U$913,CleanRef!$J$2:$J$913,"Office Supplies",CleanRef!$K$2:$K$913,"Paper",CleanRef!$AH$2:$AH$913,"Yes") -> 123501.05
A12: Technology | B12: Machines | C12: =SUMIFS(CleanRef!$T$2:$T$913,CleanRef!$J$2:$J$913,"Technology",CleanRef!$K$2:$K$913,"Machines",CleanRef!$AH$2:$AH$913,"Yes") -> 429529.93 | D12: =SUMIFS(CleanRef!$U$2:$U$913,CleanRef!$J$2:$J$913,"Technology",CleanRef!$K$2:$K$913,"Machines",CleanRef!$AH$2:$AH$913,"Yes") -> 148398.06
A13: Furniture | B13: Bookcases | C13: =SUMIFS(CleanRef!$T$2:$T$913,CleanRef!$J$2:$J$913,"Furniture",CleanRef!$K$2:$K$913,"Bookcases",CleanRef!$AH$2:$AH$913,"Yes") -> 426946.02 | D13: =SUMIFS(CleanRef!$U$2:$U$913,CleanRef!$J$2:$J$913,"Furniture",CleanRef!$K$2:$K$913,"Bookcases",CleanRef!$AH$2:$AH$913,"Yes") -> 121943.99
A14: Furniture | B14: Tables | C14: =SUMIFS(CleanRef!$T$2:$T$913,CleanRef!$J$2:$J$913,"Furniture",CleanRef!$K$2:$K$913,"Tables",CleanRef!$AH$2:$AH$913,"Yes") -> 420185.33 | D14: =SUMIFS(CleanRef!$U$2:$U$913,CleanRef!$J$2:$J$913,"Furniture",CleanRef!$K$2:$K$913,"Tables",CleanRef!$AH$2:$AH$913,"Yes") -> 127253.69
A15: Office Supplies | B15: Binders | C15: =SUMIFS(CleanRef!$T$2:$T$913,CleanRef!$J$2:$J$913,"Office Supplies",CleanRef!$K$2:$K$913,"Binders",CleanRef!$AH$2:$AH$913,"Yes") -> 342853.56 | D15: =SUMIFS(CleanRef!$U$2:$U$913,CleanRef!$J$2:$J$913,"Office Supplies",CleanRef!$K$2:$K$913,"Binders",CleanRef!$AH$2:$AH$913,"Yes") -> 109222.19
A16: Office Supplies | B16: Art | C16: =SUMIFS(CleanRef!$T$2:$T$913,CleanRef!$J$2:$J$913,"Office Supplies",CleanRef!$K$2:$K$913,"Art",CleanRef!$AH$2:$AH$913,"Yes") -> 302936.38 | D16: =SUMIFS(CleanRef!$U$2:$U$913,CleanRef!$J$2:$J$913,"Office Supplies",CleanRef!$K$2:$K$913,"Art",CleanRef!$AH$2:$AH$913,"Yes") -> 82544.723
A17: Office Supplies | B17: Labels | C17: =SUMIFS(CleanRef!$T$2:$T$913,CleanRef!$J$2:$J$913,"Office Supplies",CleanRef!$K$2:$K$913,"Labels",CleanRef!$AH$2:$AH$913,"Yes") -> 209170.53 | D17: =SUMIFS(CleanRef!$U$2:$U$913,CleanRef!$J$2:$J$913,"Office Supplies",CleanRef!$K$2:$K$913,"Labels",CleanRef!$AH$2:$AH$913,"Yes") -> 65166.618
B18: TOTAL | C18: =SUM(C5:C17) -> 6010174.4 | D18: =SUM(D5:D17) -> 1773239.4

Sheet Order Count by Ship Mode
A1: Order Count by Ship Mode (All Orders)
A3: Ship Mode | B3: Order Count | C3: % of Total Orders
A4: Standard Class | B4: =COUNTIF(CleanRef!$M$2:$M$913,"Standard Class") -> 242 | C4: =B4/COUNTA(CleanRef!$A$2:$A$913) -> 0.26535088
A5: First Class | B5: =COUNTIF(CleanRef!$M$2:$M$913,"First Class") -> 223 | C5: =B5/COUNTA(CleanRef!$A$2:$A$913) -> 0.24451754
A6: Second Class | B6: =COUNTIF(CleanRef!$M$2:$M$913,"Second Class") -> 222 | C6: =B6/COUNTA(CleanRef!$A$2:$A$913) -> 0.24342105
A7: Same Day | B7: =COUNTIF(CleanRef!$M$2:$M$913,"Same Day") -> 204 | C7: =B7/COUNTA(CleanRef!$A$2:$A$913) -> 0.22368421
A8: Unknown | B8: =COUNTIF(CleanRef!$M$2:$M$913,"Unknown") -> 21 | C8: =B8/COUNTA(CleanRef!$A$2:$A$913) -> 0.023026316
A9: TOTAL | B9: =SUM(B4:B8) -> 912

Sheet Profit Margin by Segment
A1: Profit Margin by Customer Segment (Completed Orders Only)
A4: Segment | B4: Completed Sales (₹) | C4: Completed Profit (₹) | D4: Profit Margin
A5: Home Office | B5: =SUMIFS(CleanRef!$T$2:$T$913,CleanRef!$F$2:$F$913,"Home Office",CleanRef!$AH$2:$AH$913,"Yes") -> 1564214.5 | C5: =SUMIFS(CleanRef!$U$2:$U$913,CleanRef!$F$2:$F$913,"Home Office",CleanRef!$AH$2:$AH$913,"Yes") -> 474152.64 | D5: =IF(B5=0,0,C5/B5) -> 0.30312507
A6: Consumer | B6: =SUMIFS(CleanRef!$T$2:$T$913,CleanRef!$F$2:$F$913,"Consumer",CleanRef!$AH$2:$AH$913,"Yes") -> 1472995.9 | C6: =SUMIFS(CleanRef!$U$2:$U$913,CleanRef!$F$2:$F$913,"Consumer",CleanRef!$AH$2:$AH$913,"Yes") -> 438320.58 | D6: =IF(B6=0,0,C6/B6) -> 0.29757081
A7: Corporate | B7: =SUMIFS(CleanRef!$T$2:$T$913,CleanRef!$F$2:$F$913,"Corporate",CleanRef!$AH$2:$AH$913,"Yes") -> 1312159.6 | C7: =SUMIFS(CleanRef!$U$2:$U$913,CleanRef!$F$2:$F$913,"Corporate",CleanRef!$AH$2:$AH$913,"Yes") -> 386126.62 | D7: =IF(B7=0,0,C7/B7) -> 0.29426802
A8: Small Business | B8: =SUMIFS(CleanRef!$T$2:$T$913,CleanRef!$F$2:$F$913,"Small Business",CleanRef!$AH$2:$AH$913,"Yes") -> 1660804.3 | C8: =SUMIFS(CleanRef!$U$2:$U$913,CleanRef!$F$2:$F$913,"Small Business",CleanRef!$AH$2:$AH$913,"Yes") -> 474639.52 | D8: =IF(B8=0,0,C8/B8) -> 0.28578894

Sheet Refunded-Cancelled-Failed
A1: Refunded, Cancelled & Failed Orders by Region
A3: Region | B3: Refunded (payment_status) | C3: Cancelled (order_status) | D3: Failed Payment (payment_status)
A4: East | B4: =COUNTIFS(CleanRef!$G$2:$G$913,"East",CleanRef!$Z$2:$Z$913,"Refunded") -> 14 | C4: =COUNTIFS(CleanRef!$G$2:$G$913,"East",CleanRef!$AA$2:$AA$913,"Cancelled") -> 30 | D4: =COUNTIFS(CleanRef!$G$2:$G$913,"East",CleanRef!$Z$2:$Z$913,"Failed") -> 13
A5: North | B5: =COUNTIFS(CleanRef!$G$2:$G$913,"North",CleanRef!$Z$2:$Z$913,"Refunded") -> 20 | C5: =COUNTIFS(CleanRef!$G$2:$G$913,"North",CleanRef!$AA$2:$AA$913,"Cancelled") -> 48 | D5: =COUNTIFS(CleanRef!$G$2:$G$913,"North",CleanRef!$Z$2:$Z$913,"Failed") -> 20
A6: South | B6: =COUNTIFS(CleanRef!$G$2:$G$913,"South",CleanRef!$Z$2:$Z$913,"Refunded") -> 20 | C6: =COUNTIFS(CleanRef!$G$2:$G$913,"South",CleanRef!$AA$2:$AA$913,"Cancelled") -> 35 | D6: =COUNTIFS(CleanRef!$G$2:$G$913,"South",CleanRef!$Z$2:$Z$913,"Failed") -> 20
A7: West | B7: =COUNTIFS(CleanRef!$G$2:$G$913,"West",CleanRef!$Z$2:$Z$913,"Refunded") -> 14 | C7: =COUNTIFS(CleanRef!$G$2:$G$913,"West",CleanRef!$AA$2:$AA$913,"Cancelled") -> 30 | D7: =COUNTIFS(CleanRef!$G$2:$G$913,"West",CleanRef!$Z$2:$Z$913,"Failed") -> 14
A8: Unknown | B8: =COUNTIFS(CleanRef!$G$2:$G$913,"Unknown",CleanRef!$Z$2:$Z$913,"Refunded") -> 3 | C8: =COUNTIFS(CleanRef!$G$2:$G$913,"Unknown",CleanRef!$AA$2:$AA$913,"Cancelled") -> 2 | D8: =COUNTIFS(CleanRef!$G$2:$G$913,"Unknown",CleanRef!$Z$2:$Z$913,"Failed") -> 2
A9: TOTAL | B9: =SUM(B4:B8) -> 71 | C9: =SUM(C4:C8) -> 145 | D9: =SUM(D4:D8) -> 69

Sheet Monthly Sales Trend
A1: Monthly Sales Trend (Completed Orders Only)
A4: Year-Month | B4: Completed Sales (₹) | C4: Completed Profit (₹) | D4: Completed Orders
A5: January 2024 | B5: =SUMIFS(CleanRef!$T$2:$T$913,CleanRef!$Y$2:$Y$913,2024,CleanRef!$X$2:$X$913,"January",CleanRef!$AH$2:$AH$913,"Yes") -> 257280.76 | C5: =SUMIFS(CleanRef!$U$2:$U$913,CleanRef!$Y$2:$Y$913,2024,CleanRef!$X$2:$X$913,"January",CleanRef!$AH$2:$AH$913,"Yes") -> 93253.285 | D5: =COUNTIFS(CleanRef!$Y$2:$Y$913,2024,CleanRef!$X$2:$X$913,"January",CleanRef!$AH$2:$AH$913,"Yes") -> 28
A6: February 2024 | B6: =SUMIFS(CleanRef!$T$2:$T$913,CleanRef!$Y$2:$Y$913,2024,CleanRef!$X$2:$X$913,"February",CleanRef!$AH$2:$AH$913,"Yes") -> 272999.97 | C6: =SUMIFS(CleanRef!$U$2:$U$913,CleanRef!$Y$2:$Y$913,2024,CleanRef!$X$2:$X$913,"February",CleanRef!$AH$2:$AH$913,"Yes") -> 85401.396 | D6: =COUNTIFS(CleanRef!$Y$2:$Y$913,2024,CleanRef!$X$2:$X$913,"February",CleanRef!$AH$2:$AH$913,"Yes") -> 28
A7: March 2024 | B7: =SUMIFS(CleanRef!$T$2:$T$913,CleanRef!$Y$2:$Y$913,2024,CleanRef!$X$2:$X$913,"March",CleanRef!$AH$2:$AH$913,"Yes") -> 248995 | C7: =SUMIFS(CleanRef!$U$2:$U$913,CleanRef!$Y$2:$Y$913,2024,CleanRef!$X$2:$X$913,"March",CleanRef!$AH$2:$AH$913,"Yes") -> 76783.94 | D7: =COUNTIFS(CleanRef!$Y$2:$Y$913,2024,CleanRef!$X$2:$X$913,"March",CleanRef!$AH$2:$AH$913,"Yes") -> 27
A8: April 2024 | B8: =SUMIFS(CleanRef!$T$2:$T$913,CleanRef!$Y$2:$Y$913,2024,CleanRef!$X$2:$X$913,"April",CleanRef!$AH$2:$AH$913,"Yes") -> 241541.51 | C8: =SUMIFS(CleanRef!$U$2:$U$913,CleanRef!$Y$2:$Y$913,2024,CleanRef!$X$2:$X$913,"April",CleanRef!$AH$2:$AH$913,"Yes") -> 67927.845 | D8: =COUNTIFS(CleanRef!$Y$2:$Y$913,2024,CleanRef!$X$2:$X$913,"April",CleanRef!$AH$2:$AH$913,"Yes") -> 21
A9: May 2024 | B9: =SUMIFS(CleanRef!$T$2:$T$913,CleanRef!$Y$2:$Y$913,2024,CleanRef!$X$2:$X$913,"May",CleanRef!$AH$2:$AH$913,"Yes") -> 359038.68 | C9: =SUMIFS(CleanRef!$U$2:$U$913,CleanRef!$Y$2:$Y$913,2024,CleanRef!$X$2:$X$913,"May",CleanRef!$AH$2:$AH$913,"Yes") -> 91003.629 | D9: =COUNTIFS(CleanRef!$Y$2:$Y$913,2024,CleanRef!$X$2:$X$913,"May",CleanRef!$AH$2:$AH$913,"Yes") -> 34
A10: June 2024 | B10: =SUMIFS(CleanRef!$T$2:$T$913,CleanRef!$Y$2:$Y$913,2024,CleanRef!$X$2:$X$913,"June",CleanRef!$AH$2:$AH$913,"Yes") -> 395531.12 | C10: =SUMIFS(CleanRef!$U$2:$U$913,CleanRef!$Y$2:$Y$913,2024,CleanRef!$X$2:$X$913,"June",CleanRef!$AH$2:$AH$913,"Yes") -> 116614.76 | D10: =COUNTIFS(CleanRef!$Y$2:$Y$913,2024,CleanRef!$X$2:$X$913,"June",CleanRef!$AH$2:$AH$913,"Yes") -> 33
A11: July 2024 | B11: =SUMIFS(CleanRef!$T$2:$T$913,CleanRef!$Y$2:$Y$913,2024,CleanRef!$X$2:$X$913,"July",CleanRef!$AH$2:$AH$913,"Yes") -> 235720.3 | C11: =SUMIFS(CleanRef!$U$2:$U$913,CleanRef!$Y$2:$Y$913,2024,CleanRef!$X$2:$X$913,"July",CleanRef!$AH$2:$AH$913,"Yes") -> 62651.655 | D11: =COUNTIFS(CleanRef!$Y$2:$Y$913,2024,CleanRef!$X$2:$X$913,"July",CleanRef!$AH$2:$AH$913,"Yes") -> 27
A12: August 2024 | B12: =SUMIFS(CleanRef!$T$2:$T$913,CleanRef!$Y$2:$Y$913,2024,CleanRef!$X$2:$X$913,"August",CleanRef!$AH$2:$AH$913,"Yes") -> 241428.67 | C12: =SUMIFS(CleanRef!$U$2:$U$913,CleanRef!$Y$2:$Y$913,2024,CleanRef!$X$2:$X$913,"August",CleanRef!$AH$2:$AH$913,"Yes") -> 74723.395 | D12: =COUNTIFS(CleanRef!$Y$2:$Y$913,2024,CleanRef!$X$2:$X$913,"August",CleanRef!$AH$2:$AH$913,"Yes") -> 30
A13: September 2024 | B13: =SUMIFS(CleanRef!$T$2:$T$913,CleanRef!$Y$2:$Y$913,2024,CleanRef!$X$2:$X$913,"September",CleanRef!$AH$2:$AH$913,"Yes") -> 226234.27 | C13: =SUMIFS(CleanRef!$U$2:$U$913,CleanRef!$Y$2:$Y$913,2024,CleanRef!$X$2:$X$913,"September",CleanRef!$AH$2:$AH$913,"Yes") -> 57228.045 | D13: =COUNTIFS(CleanRef!$Y$2:$Y$913,2024,CleanRef!$X$2:$X$913,"September",CleanRef!$AH$2:$AH$913,"Yes") -> 23
A14: October 2024 | B14: =SUMIFS(CleanRef!$T$2:$T$913,CleanRef!$Y$2:$Y$913,2024,CleanRef!$X$2:$X$913,"October",CleanRef!$AH$2:$AH$913,"Yes") -> 351284.32 | C14: =SUMIFS(CleanRef!$U$2:$U$913,CleanRef!$Y$2:$Y$913,2024,CleanRef!$X$2:$X$913,"October",CleanRef!$AH$2:$AH$913,"Yes") -> 100336.11 | D14: =COUNTIFS(CleanRef!$Y$2:$Y$913,2024,CleanRef!$X$2:$X$913,"October",CleanRef!$AH$2:$AH$913,"Yes") -> 30
A15: November 2024 | B15: =SUMIFS(CleanRef!$T$2:$T$913,CleanRef!$Y$2:$Y$913,2024,CleanRef!$X$2:$X$913,"November",CleanRef!$AH$2:$AH$913,"Yes") -> 260061.65 | C15: =SUMIFS(CleanRef!$U$2:$U$913,CleanRef!$Y$2:$Y$913,2024,CleanRef!$X$2:$X$913,"November",CleanRef!$AH$2:$AH$913,"Yes") -> 91770.353 | D15: =COUNTIFS(CleanRef!$Y$2:$Y$913,2024,CleanRef!$X$2:$X$913,"November",CleanRef!$AH$2:$AH$913,"Yes") -> 23
A16: December 2024 | B16: =SUMIFS(CleanRef!$T$2:$T$913,CleanRef!$Y$2:$Y$913,2024,CleanRef!$X$2:$X$913,"December",CleanRef!$AH$2:$AH$913,"Yes") -> 201157.16 | C16: =SUMIFS(CleanRef!$U$2:$U$913,CleanRef!$Y$2:$Y$913,2024,CleanRef!$X$2:$X$913,"December",CleanRef!$AH$2:$AH$913,"Yes") -> 56327.187 | D16: =COUNTIFS(CleanRef!$Y$2:$Y$913,2024,CleanRef!$X$2:$X$913,"December",CleanRef!$AH$2:$AH$913,"Yes") -> 24
A17: January 2025 | B17: =SUMIFS(CleanRef!$T$2:$T$913,CleanRef!$Y$2:$Y$913,2025,CleanRef!$X$2:$X$913,"January",CleanRef!$AH$2:$AH$913,"Yes") -> 272866.44 | C17: =SUMIFS(CleanRef!$U$2:$U$913,CleanRef!$Y$2:$Y$913,2025,CleanRef!$X$2:$X$913,"January",CleanRef!$AH$2:$AH$913,"Yes") -> 76028.785 | D17: =COUNTIFS(CleanRef!$Y$2:$Y$913,2025,CleanRef!$X$2:$X$913,"January",CleanRef!$AH$2:$AH$913,"Yes") -> 27
A18: February 2025 | B18: =SUMIFS(CleanRef!$T$2:$T$913,CleanRef!$Y$2:$Y$913,2025,CleanRef!$X$2:$X$913,"February",CleanRef!$AH$2:$AH$913,"Yes") -> 394995.72 | C18: =SUMIFS(CleanRef!$U$2:$U$913,CleanRef!$Y$2:$Y$913,2025,CleanRef!$X$2:$X$913,"February",CleanRef!$AH$2:$AH$913,"Yes") -> 117043.43 | D18: =COUNTIFS(CleanRef!$Y$2:$Y$913,2025,CleanRef!$X$2:$X$913,"February",CleanRef!$AH$2:$AH$913,"Yes") -> 39
A19: March 2025 | B19: =SUMIFS(CleanRef!$T$2:$T$913,CleanRef!$Y$2:$Y$913,2025,CleanRef!$X$2:$X$913,"March",CleanRef!$AH$2:$AH$913,"Yes") -> 322614.29 | C19: =SUMIFS(CleanRef!$U$2:$U$913,CleanRef!$Y$2:$Y$913,2025,CleanRef!$X$2:$X$913,"March",CleanRef!$AH$2:$AH$913,"Yes") -> 92228.466 | D19: =COUNTIFS(CleanRef!$Y$2:$Y$913,2025,CleanRef!$X$2:$X$913,"March",CleanRef!$AH$2:$AH$913,"Yes") -> 27
A20: April 2025 | B20: =SUMIFS(CleanRef!$T$2:$T$913,CleanRef!$Y$2:$Y$913,2025,CleanRef!$X$2:$X$913,"April",CleanRef!$AH$2:$AH$913,"Yes") -> 293107.4 | C20: =SUMIFS(CleanRef!$U$2:$U$913,CleanRef!$Y$2:$Y$913,2025,CleanRef!$X$2:$X$913,"April",CleanRef!$AH$2:$AH$913,"Yes") -> 80559.25 | D20: =COUNTIFS(CleanRef!$Y$2:$Y$913,2025,CleanRef!$X$2:$X$913,"April",CleanRef!$AH$2:$AH$913,"Yes") -> 35
A21: May 2025 | B21: =SUMIFS(CleanRef!$T$2:$T$913,CleanRef!$Y$2:$Y$913,2025,CleanRef!$X$2:$X$913,"May",CleanRef!$AH$2:$AH$913,"Yes") -> 246177.85 | C21: =SUMIFS(CleanRef!$U$2:$U$913,CleanRef!$Y$2:$Y$913,2025,CleanRef!$X$2:$X$913,"May",CleanRef!$AH$2:$AH$913,"Yes") -> 76545.446 | D21: =COUNTIFS(CleanRef!$Y$2:$Y$913,2025,CleanRef!$X$2:$X$913,"May",CleanRef!$AH$2:$AH$913,"Yes") -> 24
A22: June 2025 | B22: =SUMIFS(CleanRef!$T$2:$T$913,CleanRef!$Y$2:$Y$913,2025,CleanRef!$X$2:$X$913,"June",CleanRef!$AH$2:$AH$913,"Yes") -> 228915.65 | C22: =SUMIFS(CleanRef!$U$2:$U$913,CleanRef!$Y$2:$Y$913,2025,CleanRef!$X$2:$X$913,"June",CleanRef!$AH$2:$AH$913,"Yes") -> 67418.02 | D22: =COUNTIFS(CleanRef!$Y$2:$Y$913,2025,CleanRef!$X$2:$X$913,"June",CleanRef!$AH$2:$AH$913,"Yes") -> 27
A23: July 2025 | B23: =SUMIFS(CleanRef!$T$2:$T$913,CleanRef!$Y$2:$Y$913,2025,CleanRef!$X$2:$X$913,"July",CleanRef!$AH$2:$AH$913,"Yes") -> 258764.04 | C23: =SUMIFS(CleanRef!$U$2:$U$913,CleanRef!$Y$2:$Y$913,2025,CleanRef!$X$2:$X$913,"July",CleanRef!$AH$2:$AH$913,"Yes") -> 74288.206 | D23: =COUNTIFS(CleanRef!$Y$2:$Y$913,2025,CleanRef!$X$2:$X$913,"July",CleanRef!$AH$2:$AH$913,"Yes") -> 23
A24: August 2025 | B24: =SUMIFS(CleanRef!$T$2:$T$913,CleanRef!$Y$2:$Y$913,2025,CleanRef!$X$2:$X$913,"August",CleanRef!$AH$2:$AH$913,"Yes") -> 262335.28 | C24: =SUMIFS(CleanRef!$U$2:$U$913,CleanRef!$Y$2:$Y$913,2025,CleanRef!$X$2:$X$913,"August",CleanRef!$AH$2:$AH$913,"Yes") -> 82704.965 | D24: =COUNTIFS(CleanRef!$Y$2:$Y$913,2025,CleanRef!$X$2:$X$913,"August",CleanRef!$AH$2:$AH$913,"Yes") -> 33
A25: September 2025 | B25: =SUMIFS(CleanRef!$T$2:$T$913,CleanRef!$Y$2:$Y$913,2025,CleanRef!$X$2:$X$913,"September",CleanRef!$AH$2:$AH$913,"Yes") -> 317689.5 | C25: =SUMIFS(CleanRef!$U$2:$U$913,CleanRef!$Y$2:$Y$913,2025,CleanRef!$X$2:$X$913,"September",CleanRef!$AH$2:$AH$913,"Yes") -> 95438.908 | D25: =COUNTIFS(CleanRef!$Y$2:$Y$913,2025,CleanRef!$X$2:$X$913,"September",CleanRef!$AH$2:$AH$913,"Yes") -> 29
A26: October 2025 | B26: =SUMIFS(CleanRef!$T$2:$T$913,CleanRef!$Y$2:$Y$913,2025,CleanRef!$X$2:$X$913,"October",CleanRef!$AH$2:$AH$913,"Yes") -> 121434.8 | C26: =SUMIFS(CleanRef!$U$2:$U$913,CleanRef!$Y$2:$Y$913,2025,CleanRef!$X$2:$X$913,"October",CleanRef!$AH$2:$AH$913,"Yes") -> 36962.274 | D26: =COUNTIFS(CleanRef!$Y$2:$Y$913,2025,CleanRef!$X$2:$X$913,"October",CleanRef!$AH$2:$AH$913,"Yes") -> 10
A27: November 2025 | B27: =SUMIFS(CleanRef!$T$2:$T$913,CleanRef!$Y$2:$Y$913,2025,CleanRef!$X$2:$X$913,"November",CleanRef!$AH$2:$AH$913,"Yes") -> 0 | C27: =SUMIFS(CleanRef!$U$2:$U$913,CleanRef!$Y$2:$Y$913,2025,CleanRef!$X$2:$X$913,"November",CleanRef!$AH$2:$AH$913,"Yes") -> 0 | D27: =COUNTIFS(CleanRef!$Y$2:$Y$913,2025,CleanRef!$X$2:$X$913,"November",CleanRef!$AH$2:$AH$913,"Yes") -> 0
A28: December 2025 | B28: =SUMIFS(CleanRef!$T$2:$T$913,CleanRef!$Y$2:$Y$913,2025,CleanRef!$X$2:$X$913,"December",CleanRef!$AH$2:$AH$913,"Yes") -> 0 | C28: =SUMIFS(CleanRef!$U$2:$U$913,CleanRef!$Y$2:$Y$913,2025,CleanRef!$X$2:$X$913,"December",CleanRef!$AH$2:$AH$913,"Yes") -> 0 | D28: =COUNTIFS(CleanRef!$Y$2:$Y$913,2025,CleanRef!$X$2:$X$913,"December",CleanRef!$AH$2:$AH$913,"Yes") -> 0
A29: TOTAL | B29: =SUM(B5:B28) -> 6010174.4 | C29: =SUM(C5:C28) -> 1773239.4 | D29: =SUM(D5:D28) -> 602

Sheet CleanRef
A1: order_id | B1: order_date | C1: ship_date | D1: customer_id | E1: customer_name | F1: segment | G1: region | H1: state | I1: city | J1: category | K1: sub_category | L1: product_name | M1: ship_mode | N1: quantity | O1: unit_price | P1: discount_parsed | Q1: cleaned_discount | R1: recorded_sales | S1: cost | T1: calculated_sales | U1: calculated_profit | V1: profit_margin | W1: shipping_delay_days | X1: order_month | Y1: order_year | Z1: payment_status | AA1: order_status | AB1: is_region_filled | AC1: is_shipmode_filled | AD1: is_discount_filled | AE1: is_shipping_invalid | AF1: is_discount_invalid | AG1: is_duplicate_conflict | AH1: is_completed_sale | AI1: data_quality_flag | AJ1: raw_order_date | AK1: raw_ship_date | AL1: raw_customer_name | AM1: raw_segment | AN1: raw_region | AO1: raw_state | AP1: raw_city | AQ1: raw_category | AR1: raw_sub_category | AS1: raw_ship_mode | AT1: raw_discount | AU1: raw_payment_status | AV1: raw_order_status
A2: ORD-2024-10001 | B2: 45494 | C2: 45500 | D2: CUST-4655 | E2: Karan Malhotra | F2: Consumer | G2: North | H2: Rajasthan | I2: Jaipur | J2: Office Supplies | K2: Paper | M2: Second Class | N2: 8 | O2: 2976.45 | P2: 0.2 | Q2: 0.2 | R2: 19049.28 | S2: 15841.89 | T2: 19049.28 | U2: 3207.39 | V2: 0.16837329 | W2: 6 | X2: July | Y2: 2024 | Z2: Paid | AA2: Completed | AB2: No | AC2: No | AD2: No | AE2: No | AF2: No | AG2: No | AH2: Yes | AI2: Clean | AJ2: 21 Jul 2024 | AK2: 07/27/2024 | AL2: Karan Malhotra | AM2: Consumer | AN2: North | AO2: Rajasthan | AP2: Jaipur | AQ2: Office Supplies | AR2: Paper | AS2: Second Class | AT2: 0.2 | AU2: Paid | AV2: Completed
A3: ORD-2024-10002 | B3: 45535 | C3: 45540 | D3: CUST-2054 | E3: Mira Das | F3: Small Business | G3: East | H3: Odisha | I3: Bhubaneswar | J3: Furniture | K3: Tables | M3: Same Day | N3: 3 | O3: 2437.5 | P3: 0 | Q3: 0 | R3: 7312.5 | S3: 4904.73 | T3: 7312.5 | U3: 2407.77 | V3: 0.32926769 | W3: 5 | X3: August | Y3: 2024 | Z3: Paid | AA3: Completed | AB3: No | AC3: No | AD3: No | AE3: No | AF3: No | AG3: No | AH3: Yes | AI3: Clean | AJ3: 08/31/2024 | AK3: 05 Sep 2024 | AL3: Mira Das | AM3: Small Business | AN3: East | AO3: Odisha | AP3: Bhubaneswar | AQ3: Furniture | AR3: Tables | AS3: Same Day | AT3: 0 | AU3: Paid | AV3: Completed
A4: ORD-2024-10003 | B4: 45451 | C4: 45458 | D4: CUST-6843 | E4: Isha Nair | F4: Consumer | G4: East | H4: Odisha | I4: Bhubaneswar | J4: Office Supplies | K4: Art | M4: First Class | N4: 4 | O4: 1065.43 | P4: 0.55 | Q4: 0 | R4: 4261.72 | S4: 2465.69 | T4: 4261.72 | U4: 1796.03 | V4: 0.42143313 | W4: 7 | X4: June | Y4: 2024 | Z4: Paid | AA4: Completed | AB4: No | AC4: No | AD4: No | AE4: No | AF4: Yes | AG4: No | AH4: Yes | AI4: Invalid | AJ4: 06/08/2024 | AK4: 15 Jun 2024 | AL4: Isha Nair | AM4: Consumer | AN4: East | AO4: Odisha | AP4: Bhubaneswar | AQ4: Office Supplies | AR4: Art | AS4: First Class | AT4: 0.55 | AU4: Paid | AV4: Completed
A5: ORD-2024-10004 | B5: 45624 | C5: 45625 | D5: CUST-3722 | E5: Arjun Bose | F5: Small Business | G5: South | H5: Telangana | I5: Hyderabad | J5: Furniture | K5: Furnishings | M5: Standard Class | N5: 6 | O5: 1848.43 | P5: 0.25 | Q5: 0.25 | R5: 8317.93 | S5: 6796.77 | T5: 8317.935 | U5: 1521.165 | V5: 0.18287772 | W5: 1 | X5: November | Y5: 2024 | Z5: Paid | AA5: Completed | AB5: No | AC5: No | AD5: No | AE5: No | AF5: No | AG5: No | AH5: Yes | AI5: Clean | AJ5: 28-11-2024 | AK5: 11/29/2024 | AL5: Arjun Bose | AM5: Small Business | AN5: South | AO5: Telangana | AP5: Hyderabad | AQ5: Furniture | AR5: Furnishings | AS5: Standard Class | AT5: 0.25 | AU5: Paid | AV5: Completed
A6: ORD-2025-10005 | B6: 45898 | C6: 45901 | D6: CUST-8130 | E6: Ananya Rao | F6: Small Business | G6: West | H6: Maharashtra | I6: Mumbai | J6: Furniture | K6: Chairs | M6: First Class | N6: 7 | O6: 2973.76 | P6: 0 | Q6: 0 | R6: 20816.32 | S6: 17705.37 | T6: 20816.32 | U6: 3110.95 | V6: 0.14944764 | W6: 3 | X6: August | Y6: 2025 | Z6: Paid | AA6: Cancelled | AB6: No | AC6: No | AD6: No | AE6: No | AF6: No | AG6: No | AH6: No | AI6: Clean | AJ6: 29 Aug 2025 | AK6: 2025-09-01 | AL6: Ananya Rao | AM6: Small Business | AN6: West | AO6: Maharashtra | AP6: Mumbai | AQ6: Furniture | AR6: Chairs | AS6: First Class | AT6: 0 | AU6: Paid | AV6: Cancelled
A7: ORD-2024-10006 | B7: 45436 | C7: 45440 | D7: CUST-6056 | E7: Vikram Iyer | F7: Small Business | G7: West | H7: Madhya Pradesh | I7: Indore | J7: Technology | K7: Accessories | M7: Same Day | N7: 3 | O7: 1053.11 | P7: 0.2 | Q7: 0.2 | R7: 2527.46 | S7: 1533.58 | T7: 2527.464 | U7: 993.884 | V7: 0.39323369 | W7: 4 | X7: May | Y7: 2024 | Z7: Paid | AA7: Completed | AB7: No | AC7: No | AD7: No | AE7: No | AF7: No | AG7: No | AH7: Yes | AI7: Clean | AJ7: 2024-05-24 | AK7: 28-05-2024 | AL7: Vikram Iyer | AM7: Small Business | AN7: West | AO7: Madhya Pradesh | AP7: Indore | AQ7: Technology | AR7: Accessories | AS7: Same Day | AT7: 0.2 | AU7: Paid | AV7: Completed
A8: ORD-2025-10007 | B8: 45757 | C8: 45763 | D8: CUST-3656 | E8: Neha Gupta | F8: Consumer | G8: East | H8: Odisha | I8: Bhubaneswar | J8: Technology | K8: Copiers | M8: Standard Class | N8: 4 | O8: 1719.87 | P8: 0.15 | Q8: 0.15 | R8: 5847.56 | S8: 4727.25 | T8: 5847.558 | U8: 1120.308 | V8: 0.19158562 | W8: 6 | X8: April | Y8: 2025 | Z8: Paid | AA8: Completed | AB8: No | AC8: No | AD8: No | AE8: No | AF8: No | AG8: No | AH8: Yes | AI8: Clean | AJ8: 04/10/2025 | AK8: 04/16/2025 | AL8: Neha Gupta | AM8: Consumer | AN8: East | AO8: Odisha | AP8: Bhubaneswar | AQ8: Technology | AR8: Copiers | AS8: Standard Class | AT8: 0.15 | AU8: Paid | AV8: Completed
A9: ORD-2025-10008 | B9: 45711 | C9: 45714 | D9: CUST-4683 | E9: Isha Nair | F9: Small Business | G9: South | H9: Andhra Pradesh | I9: Vijayawada | J9: Office Supplies | K9: Art | M9: First Class | N9: 1 | O9: 2980.71 | P9: 0 | Q9: 0 | R9: 2980.71 | S9: 2357.22 | T9: 2980.71 | U9: 623.49 | V9: 0.209175 | W9: 3 | X9: February | Y9: 2025 | Z9: Paid | AA9: Completed | AB9: No | AC9: No | AD9: No | AE9: No | AF9: No | AG9: No | AH9: Yes | AI9: Clean | AJ9: 2025-02-23 | AK9: 26-02-2025 | AL9: Isha Nair | AM9: Small Business | AN9: South | AO9: Andhra Pradesh | AP9: Vijayawada | AQ9: Office Supplies | AR9: Art | AS9: First Class | AT9: 0 | AU9: Paid | AV9: Completed
A10: ORD-2024-10009 | B10: 45601 | C10: 45606 | D10: CUST-2598 | E10: Aditi Sen | F10: Corporate | G10: South | H10: Telangana | I10: Hyderabad | J10: Office Supplies | K10: Labels | M10: First Class | N10: 8 | O10: 3134.2 | P10: 0 | Q10: 0 | R10: 25073.6 | S10: 17347.23 | T10: 25073.6 | U10: 7726.37 | V10: 0.30814761 | W10: 5 | X10: November | Y10: 2024 | Z10: Paid | AA10: Completed | AB10: No | AC10: No | AD10: No | AE10: No | AF10: No | AG10: No | AH10: Yes | AI10: Clean | AJ10: 11/05/2024 | AK10: 11/10/2024 | AL10: Aditi Sen | AM10: Corporate | AN10: South | AO10: Telangana | AP10: Hyderabad | AQ10: Office Supplies | AR10: Labels | AS10: First Class | AT10: 0 | AU10: Paid | AV10: Completed
A11: ORD-2025-10010 | B11: 45907 | C11: 45912 | D11: CUST-2483 | E11: Mira Das | F11: Home Office | G11: South | H11: Telangana | I11: Hyderabad | J11: Office Supplies | K11: Paper | M11: Second Class | N11: 9 | O11: 852.04 | P11: 0.2 | Q11: 0.2 | R11: 6134.69 | S11: 3800.19 | T11: 6134.688 | U11: 2334.498 | V11: 0.38054062 | W11: 5 | X11: September | Y11: 2025 | Z11: Paid | AA11: Completed | AB11: No | AC11: No | AD11: No | AE11: No | AF11: No | AG11: No | AH11: Yes | AI11: Clean | AJ11: 07-09-2025 | AK11: 09/12/2025 | AL11: Mira Das | AM11: Home Office | AN11: South | AO11: Telangana | AP11: Hyderabad | AQ11: Office Supplies | AR11: Paper | AS11: Second Class | AT11: 0.2 | AU11: Paid | AV11: Completed
A12: ORD-2025-10011 | B12: 45797 | C12: 45797 | D12: CUST-8092 | E12: Ananya Rao | F12: Corporate | G12: East | H12: West Bengal | I12: Kolkata | J12: Office Supplies | K12: Labels | M12: Second Class | N12: 3 | O12: 3534.83 | P12: 0.05 | Q12: 0.05 | R12: 10074.27 | S12: 6048.27 | T12: 10074.265 | U12: 4025.9955 | V12: 0.39963167 | W12: 0 | X12: May | Y12: 2025 | Z12: Refunded | AA12: Returned | AB12: No | AC12: No | AD12: No | AE12: No | AF12: No | AG12: No | AH12: No | AI12: Clean | AJ12: 20 May 2025 | AK12: 05/20/2025 | AL12: Ananya Rao | AM12: Corporate | AN12: East | AO12: West Bengal | AP12: Kolkata | AQ12: Office Supplies | AR12: Labels | AS12: Second Class | AT12: 0.05 | AU12: Refunded | AV12: Returned
A13: ORD-2024-10012 | B13: 45495 | C13: 45496 | D13: CUST-6528 | E13: Vikram Iyer | F13: Small Business | G13: East | H13: Odisha | I13: Bhubaneswar | J13: Technology | K13: Accessories | M13: Same Day | N13: 6 | O13: 2005.95 | P13: 0.2 | Q13: 0.2 | R13: 9628.56 | S13: 8038.59 | T13: 9628.56 | U13: 1589.97 | V13: 0.16513061 | W13: 1 | X13: July | Y13: 2024 | Z13: Paid | AA13: Completed | AB13: No | AC13: No | AD13: No | AE13: No | AF13: No | AG13: No | AH13: Yes | AI13: Clean | AJ13: 2024-07-22 | AK13: 23-07-2024 | AL13: Vikram Iyer | AM13: Small Business | AN13: East | AO13: Odisha | AP13: Bhubaneswar | AQ13: Technology | AR13: Accessories | AS13: Same Day | AT13: 0.2 | AU13: Paid | AV13: Completed
... A33: ORD-2025-10032 | B33: 45823 | C33: 45827 | D33: CUST-7867 | E33: Karan Malhotra | F33: Small Business | G33: West | H33: Madhya Pradesh | I33: Indore | J33: Office Supplies | K33: Paper | M33: Second Class | N33: 9 | O33: 3092.55 | P33: 0 | Q33: 0 | R33: 27832.95 | S33: 17769.75 | T33: 27832.95 | U33: 10063.2 | V33: 0.36155708 | W33: 4 | X33: June | Y33: 2025 | Z33: Failed | AA33: Returned | AB33: No | AC33: No | AD33: No | AE33: No | AF33: No | AG33: No | AH33: No | AI33: Clean | AJ33: 15-06-2025 | AK33: 19-06-2025 | AL33: Karan Malhotra | AM33: Small Business | AN33: West | AO33: Madhya Pradesh | AP33: Indore | AQ33: Office Supplies | AR33: Paper | AS33: Second Class | AT33: 0 | AU33: Failed | AV33: Returned
A34: ORD-2024-10033 | B34: 45618 | C34: 45622 | D34: CUST-6509 | E34: Aarav Sharma | F34: Corporate | G34: South | H34: Andhra Pradesh | I34: Vijayawada | J34: Technology | K34: Phones | M34: Second Class | N34: 3 | O34: 4001.25 | Q34: 0 | R34: 9002.81 | S34: 7529.92 | T34: 12003.75 | U34: 4473.83 | V34: 0.3727027 | W34: 4 | X34: November | Y34: 2024 | Z34: Paid | AA34: Completed | AB34: No | AC34: No | AD34: Yes | AE34: No | AF34: No | AG34: No | AH34: Yes | AI34: Warning | AJ34: 22-11-2024 | AK34: 2024-11-26 | AL34: Aarav Sharma | AM34: Corporate | AN34: South | AO34: Andhra Pradesh | AP34: Vijayawada | AQ34: Technology | AR34: Phones | AS34: Second Class | AU34: Paid | AV34: Completed
A35: ORD-2024-10034 | B35: 45495 | C35: 45500 | D35: CUST-6660 | E35: Priya Menon | F35: Home Office | G35: West | H35: Goa | I35: Panaji | J35: Furniture | K35: Tables | M35: Same Day | N35: 7 | O35: 492.41 | P35: 0.25 | Q35: 0.25 | R35: 2585.15 | S35: 2070.73 | T35: 2585.1525 | U35: 514.4225 | V35: 0.19899116 | W35: 5 | X35: July | Y35: 2024 | Z35: Paid | AA35: Completed | AB35: No | AC35: No | AD35: No | AE35: No | AF35: No | AG35: No | AH35: Yes | AI35: Clean | AJ35: 07/22/2024 | AK35: 27-07-2024 | AL35: Priya Menon | AM35: Home Office | AN35: West | AO35: Goa | AP35: Panaji | AQ35: Furniture | AR35: Tables | AS35: Same Day | AT35: 0.25 | AU35: Paid | AV35: Completed
A36: ORD-2025-10035 | B36: 45688 | C36: 45693 | D36: CUST-2392 | E36: Priya Menon | F36: Home Office | G36: East | H36: West Bengal | I36: Kolkata | J36: Furniture | K36: Chairs | M36: Unknown | N36: 2 | O36: 4159.69 | P36: 0.2 | Q36: 0.2 | R36: 6655.5 | S36: 4340.21 | T36: 6655.504 | U36: 2315.294 | V36: 0.34787658 | W36: 5 | X36: January | Y36: 2025 | Z36: Paid | AA36: Completed | AB36: No | AC36: Yes | AD36: No | AE36: No | AF36: No | AG36: No | AH36: Yes | AI36: Warning | AJ36: 2025-01-31 | AK36: 2025-02-05 | AL36: Priya Menon | AM36: Home Office | AN36: East | AO36: West Bengal | AP36: Kolkata | AQ36: Furniture | AR36: Chairs | AT36: 0.2 | AU36: Paid | AV36: Completed
A37: ORD-2024-10036 | B37: 45441 | C37: 45441 | D37: CUST-1611 | E37: Sneha Kapoor | F37: Small Business | G37: West | H37: Gujarat | I37: Ahmedabad | J37: Furniture | K37: Bookcases | M37: Second Class | N37: 8 | O37: 2507.12 | P37: 0.05 | Q37: 0.05 | R37: 19054.11 | S37: 15313.83 | T37: 19054.112 | U37: 3740.282 | V37: 0.19629789 | W37: 0 | X37: May | Y37: 2024 | Z37: Pending | AA37: Returned | AB37: No | AC37: No | AD37: No | AE37: No | AF37: No | AG37: No | AH37: No | AI37: Clean | AJ37: 29-05-2024 | AK37: 29 May 2024 | AL37: Sneha Kapoor | AM37: Small Business | AN37: West | AO37: Gujarat | AP37: Ahmedabad | AQ37: Furniture | AR37: Bookcases | AS37: Second Class | AT37: 0.05 | AU37: Pending | AV37: Returned
A38: ORD-2024-10037 | B38: 45590 | C38: 45593 | D38: CUST-8296 | E38: Rohan Mehta | F38: Corporate | G38: West | H38: Maharashtra | I38: Mumbai | J38: Furniture | K38: Bookcases | M38: Second Class | N38: 3 | O38: 3126.47 | P38: 0 | Q38: 0 | R38: 9379.41 | S38: 6670.85 | T38: 9379.41 | U38: 2708.56 | V38: 0.28877723 | W38: 3 | X38: October | Y38: 2024 | Z38: Paid | AA38: Returned | AB38: No | AC38: No | AD38: No | AE38: No | AF38: No | AG38: No | AH38: No | AI38: Clean | AJ38: 2024-10-25 | AK38: 28 Oct 2024 | AL38: Rohan Mehta | AM38: Corporate | AN38: West | AO38: Maharashtra | AP38: Mumbai | AQ38: Furniture | AR38: Bookcases | AS38: Second Class | AT38: 0 | AU38: Paid | AV38: Returned
A39: ORD-2025-10038 | B39: 45867 | C39: 45867 | D39: CUST-4646 | E39: Diya Patel | F39: Consumer | G39: West | H39: Maharashtra | I39: Mumbai | J39: Technology | K39: Copiers | M39: Standard Class | N39: 4 | O39: 1327.54 | P39: 0.2 | Q39: 0.2 | R39: 4248.13 | S39: 3321.09 | T39: 4248.128 | U39: 927.038 | V39: 0.21822271 | W39: 0 | X39: July | Y39: 2025 | Z39: Paid | AA39: Completed | AB39: No | AC39: No | AD39: No | AE39: No | AF39: No | AG39: No | AH39: Yes | AI39: Clean | AJ39: 29-07-2025 | AK39: 29-07-2025 | AL39: Diya Patel | AM39: Consumer | AN39: West | AO39: Maharashtra | AP39: Mumbai | AQ39: Technology | AR39: Copiers | AS39: STANDARD CLASS | AT39: 0.2 | AU39: Paid | AV39: Completed
A40: ORD-2024-10039 | B40: 45460 | C40: 45465 | D40: CUST-8235 | E40: Aarav Sharma | F40: Corporate | G40: West | H40: Gujarat | I40: Ahmedabad | J40: Technology | K40: Phones | M40: First Class | N40: 7 | O40: 2210.68 | P40: 0.1 | Q40: 0.1 | R40: 13927.28 | S40: 10504.87 | T40: 13927.284 | U40: 3422.414 | V40: 0.24573449 | W40: 5 | X40: June | Y40: 2024 | Z40: Paid | AA40: Completed | AB40: No | AC40: No | AD40: No | AE40: No | AF40: No | AG40: No | AH40: Yes | AI40: Clean | AJ40: 2024-06-17 | AK40: 22-06-2024 | AL40: Aarav Sharma | AM40: Corporate | AN40: West | AO40: Gujarat | AP40: Ahmedabad | AQ40: Technology | AR40: Phones | AS40: First Class | AT40: 0.1 | AU40: Paid | AV40: Completed
A41: ORD-2024-10040 | B41: 45637 | C41: 45637 | D41: CUST-5830 | E41: Mira Das | F41: Small Business | G41: West | H41: Madhya Pradesh | I41: Indore | J41: Technology | K41: Copiers | M41: First Class | N41: 4 | O41: 1370.92 | P41: 0.1 | Q41: 0.1 | R41: 4935.31 | S41: 3374.77 | T41: 4935.312 | U41: 1560.542 | V41: 0.31619926 | W41: 0 | X41: December | Y41: 2024 | Z41: Pending | AA41: Returned | AB41: No | AC41: No | AD41: No | AE41: No | AF41: No | AG41: No | AH41: No | AI41: Clean | AJ41: 12/11/2024 | AK41: 2024-12-11 | AL41: Mira Das | AM41: Small Business | AN41: West | AO41: Madhya Pradesh | AP41: Indore | AQ41: Technology | AR41: Copiers | AS41: First Class | AT41: 0.1 | AU41: Pending | AV41: Returned
A42: ORD-2024-10041 | B42: 45575 | C42: 45581 | D42: CUST-7178 | E42: Isha Nair | F42: Home Office | G42: West | H42: Rajasthan | I42: Udaipur | J42: Technology | K42: Copiers | M42: Standard Class | N42: 7 | O42: 2509.27 | P42: 0.2 | Q42: 0.2 | R42: 14051.91 | S42: 11990.37 | T42: 14051.912 | U42: 2061.542 | V42: 0.146709 | W42: 6 | X42: October | Y42: 2024 | Z42: Paid | AA42: Completed | AB42: No | AC42: No | AD42: No | AE42: No | AF42: No | AG42: No | AH42: Yes | AI42: Clean | AJ42: 10-10-2024 | AK42: 16 Oct 2024 | AL42: Isha Nair | AM42: Home Office | AN42: West | AO42: Rajasthan | AP42: Udaipur | AQ42: Technology | AR42: Copiers | AS42: Standard Class | AT42: 0.2 | AU42: Paid | AV42: Completed
A43: ORD-2024-10042 | B43: 45363 | C43: 45368 | D43: CUST-3829 | E43: Aarav Sharma | F43: Small Business | G43: East | H43: Odisha | I43: Bhubaneswar | J43: Furniture | K43: Bookcases | M43: Same Day | N43: 8 | O43: 855.81 | P43: 0 | Q43: 0 | R43: 6846.48 | S43: 4239.89 | T43: 6846.48 | U43: 2606.59 | V43: 0.38071973 | W43: 5 | X43: March | Y43: 2024 | Z43: Pending | AA43: Cancelled | AB43: No | AC43: No | AD43: No | AE43: No | AF43: No | AG43: No | AH43: No | AI43: Clean | AJ43: 03/12/2024 | AK43: 17-03-2024 | AL43: Aarav Sharma | AM43: Small Business | AN43: East | AO43: Odisha | AP43: Bhubaneswar | AQ43: Furniture | AR43: Bookcases | AS43: Same Day | AT43: 0 | AU43: Pending | AV43: Cancelled
A44: ORD-2025-10043 | B44: 45940 | C44: 45945 | D44: CUST-6708 | E44: Arjun Bose | F44: Corporate | G44: East | H44: Jharkhand | I44: Ranchi | J44: Technology | K44: Phones | M44: Standard Class | N44: 8 | O44: 979.87 | P44: 0.05 | Q44: 0.05 | R44: 7447.01 | S44: 4496.22 | T44: 7447.012 | U44: 2950.792 | V44: 0.39623838 | W44: 5 | X44: October | Y44: 2025 | Z44: Paid | AA44: Completed | AB44: No | AC44: No | AD44: No | AE44: No | AF44: No | AG44: No | AH44: Yes | AI44: Clean | AJ44: 2025-10-10 | AK44: 15 Oct 2025 | AL44: Arjun Bose | AM44: Corporate | AN44: East | AO44: Jharkhand | AP44: Ranchi | AQ44: Technology | AR44: Phones | AS44: Standard Class | AT44: 0.05 | AU44: Paid | AV44: Completed
A45: ORD-2024-10044 | B45: 45481 | C45: 45487 | D45: CUST-7119 | E45: Priya Menon | F45: Small Business | G45: East | H45: Odisha | I45: Bhubaneswar | J45: Furniture | K45: Furnishings | M45: Same Day | N45: 3 | O45: 1010.23 | P45: 0 | Q45: 0 | R45: 3030.69 | S45: 1721.08 | T45: 3030.69 | U45: 1309.61 | V45: 0.43211612 | W45: 6 | X45: July | Y45: 2024 | Z45: Paid | AA45: Completed | AB45: No | AC45: No | AD45: No | AE45: No | AF45: No | AG45: No | AH45: Yes | AI45: Clean | AJ45: 07/08/2024 | AK45: 07/14/2024 | AL45: Priya Menon | AM45: Small Business | AN45: East | AO45: Odisha | AP45: Bhubaneswar | AQ45: Furniture | AR45: Furnishings | AS45: Same Day | AT45: 0 | AU45: Paid | AV45: Completed
A46: ORD-2024-10045 | B46: 45465 | C46: 45468 | D46: CUST-3373 | E46: Rohan Mehta | F46: Small Business | G46: North | H46: Haryana | I46: Gurugram | J46: Furniture | K46: Chairs | M46: Standard Class | N46: 9 | O46: 3329.77 | P46: 0.1 | Q46: 0.1 | R46: 26971.14 | S46: 17376.2 | T46: 26971.137 | U46: 9594.937 | V46: 0.35574833 | W46: 3 | X46: June | Y46: 2024 | Z46: Paid | AA46: Completed | AB46: No | AC46: No | AD46: No | AE46: No | AF46: No | AG46: No | AH46: Yes | AI46: Clean | AJ46: 06/22/2024 | AK46: 25-06-2024 | AL46: Rohan Mehta | AM46: Small Business | AN46: North | AO46: Haryana | AP46: Gurugram | AQ46: Furniture | AR46: Chairs | AS46: Standard Class | AT46: 0.1 | AU46: Paid | AV46: Completed
A47: ORD-2024-10046 | B47: 45309 | C47: 45315 | D47: CUST-8896 | E47: Isha Nair | F47: Home Office | G47: East | H47: Bihar | I47: Patna | J47: Office Supplies | K47: Art | M47: Second Class | N47: 8 | O47: 3927.82 | P47: 0.05 | Q47: 0.05 | R47: 29851.43 | S47: 17487.48 | T47: 29851.432 | U47: 12363.952 | V47: 0.41418288 | W47: 6 | X47: January | Y47: 2024 | Z47: Pending | AA47: Returned | AB47: No | AC47: No | AD47: No | AE47: No | AF47: No | AG47: No | AH47: No | AI47: Clean | AJ47: 18 Jan 2024 | AK47: 24-01-2024 | AL47: Isha Nair | AM47: Home Office | AN47: East | AO47: Bihar | AP47: Patna | AQ47: Office Supplies | AR47: Art | AS47: Second Class | AT47: 0.05 | AU47: Pending | AV47: Returned
A48: ORD-2024-10047 | B48: 45492 | C48: 45492 | D48: CUST-8517 | E48: Ananya Rao | F48: Small Business | G48: South | H48: Kerala | I48: Kochi | J48: Furniture | K48: Bookcases | M48: Standard Class | N48: 9 | O48: 2386.79 | P48: 0.25 | Q48: 0.25 | R48: 16110.83 | S48: 10680.03 | T48: 16110.833 | U48: 5430.8025 | V48: 0.33709012 | W48: 0 | X48: July | Y48: 2024 | Z48: Refunded | AA48: Returned | AB48: No | AC48: No | AD48: No | AE48: No | AF48: No | AG48: No | AH48: No | AI48: Clean | AJ48: 19-07-2024 | AK48: 19-07-2024 | AL48: Ananya Rao | AM48: Small Business | AN48: South | AO48: Kerala | AP48: Kochi | AQ48: Furniture | AR48: Bookcases | AS48: Standard Class | AT48: 0.25 | AU48: Refunded | AV48: Returned
... A59: ORD-2024-10058 | B59: 45329 | C59: 45337 | D59: CUST-9941 | E59: Priya Menon | F59: Consumer | G59: West | H59: Goa | I59: Panaji | J59: Furniture | K59: Chairs | M59: Same Day | N59: 5 | O59: 255.87 | P59: 0 | Q59: 0 | R59: 1279.35 | S59: 1091.54 | T59: 1279.35 | U59: 187.81 | V59: 0.14680111 | W59: 8 | X59: February | Y59: 2024 | Z59: Paid | AA59: Completed | AB59: No | AC59: No | AD59: No | AE59: No | AF59: No | AG59: No | AH59: Yes | AI59: Clean | AJ59: 2024-02-07 | AK59: 15 Feb 2024 | AL59: Priya Menon | AM59: Consumer | AN59: West | AO59: Goa | AP59: Panaji | AQ59: Furniture | AR59: Chairs | AS59: Same Day | AT59: 0 | AU59: Paid | AV59: Completed
A60: ORD-2024-10059 | B60: 45536 | C60: 45542 | D60: CUST-3983 | E60: Isha Nair | F60: Home Office | G60: North | H60: Rajasthan | I60: Jaipur | J60: Office Supplies | K60: Storage | M60: Unknown | N60: 9 | O60: 1389.48 | P60: 0.1 | Q60: 0.1 | R60: 11254.79 | S60: 6578.06 | T60: 11254.788 | U60: 4676.728 | V60: 0.41553231 | W60: 6 | X60: September | Y60: 2024 | Z60: Pending | AA60: Returned | AB60: No | AC60: Yes | AD60: No | AE60: No | AF60: No | AG60: No | AH60: No | AI60: Warning | AJ60: 2024-09-01 | AK60: 2024-09-07 | AL60: Isha Nair | AM60: Home Office | AN60: North | AO60: Rajasthan | AP60: Jaipur | AQ60: Office Supplies | AR60: Storage | AT60: 0.1 | AU60: Pending | AV60: Returned
A61: ORD-2024-10060 | B61: 45493 | C61: 45498 | D61: CUST-2418 | E61: Priya Menon | F61: Corporate | G61: East | H61: Assam | I61: Guwahati | J61: Office Supplies | K61: Labels | M61: Same Day | N61: 5 | O61: 4133.85 | P61: 0.2 | Q61: 0.2 | R61: 16535.4 | S61: 12990.21 | T61: 16535.4 | U61: 3545.19 | V61: 0.21440001 | W61: 5 | X61: July | Y61: 2024 | Z61: Paid | AA61: Cancelled | AB61: No | AC61: No | AD61: No | AE61: No | AF61: No | AG61: No | AH61: No | AI61: Clean | AJ61: 20-07-2024 | AK61: 25 Jul 2024 | AL61: Priya Menon | AM61: Corporate | AN61: East | AO61: Assam | AP61: Guwahati | AQ61: Office Supplies | AR61: Labels | AS61: Same Day | AT61: 0.2 | AU61: Paid | AV61: Cancelled
A62: ORD-2024-10061 | B62: 45486 | C62: 45492 | D62: CUST-2892 | E62: Ananya Rao | F62: Corporate | G62: East | H62: Assam | I62: Guwahati | J62: Office Supplies | K62: Labels | M62: Same Day | N62: 3 | O62: 275.76 | P62: 0.2 | Q62: 0.2 | R62: 661.82 | S62: 481.47 | T62: 661.824 | U62: 180.354 | V62: 0.27251052 | W62: 6 | X62: July | Y62: 2024 | Z62: Refunded | AA62: Cancelled | AB62: No | AC62: No | AD62: No | AE62: No | AF62: No | AG62: No | AH62: No | AI62: Clean | AJ62: 07/13/2024 | AK62: 2024-07-19 | AL62: Ananya Rao | AM62: Corporate | AN62: East | AO62: Assam | AP62: Guwahati | AQ62: Office Supplies | AR62: Labels | AS62: Same Day | AT62: 0.2 | AU62: Refunded | AV62: Cancelled
A63: ORD-2024-10062 | B63: 45398 | C63: 45398 | D63: CUST-7008 | E63: Vikram Iyer | F63: Home Office | G63: East | H63: Bihar | I63: Patna | J63: Furniture | K63: Bookcases | M63: Standard Class | N63: 1 | O63: 949.59 | P63: 0 | Q63: 0 | R63: 949.59 | S63: 751.25 | T63: 949.59 | U63: 198.34 | V63: 0.20886909 | W63: 0 | X63: April | Y63: 2024 | Z63: Paid | AA63: Completed | AB63: No | AC63: No | AD63: No | AE63: No | AF63: No | AG63: No | AH63: Yes | AI63: Clean | AJ63: 16 Apr 2024 | AK63: 04/16/2024 | AL63: Vikram Iyer | AM63: Home Office | AN63: East | AO63: Bihar | AP63: Patna | AQ63: Furniture | AR63: Bookcases | AS63: Standard Class | AT63: 0 | AU63: Paid | AV63: Completed
A64: ORD-2024-10063 | B64: 45595 | C64: 45598 | D64: CUST-4900 | E64: Sneha Kapoor | F64: Home Office | G64: North | H64: Rajasthan | I64: Jaipur | J64: Technology | K64: Phones | M64: Standard Class | N64: 9 | O64: 3042.29 | P64: 0.2 | Q64: 0.2 | R64: 21904.49 | S64: 13570.55 | T64: 21904.488 | U64: 8333.938 | V64: 0.38046714 | W64: 3 | X64: October | Y64: 2024 | Z64: Paid | AA64: Completed | AB64: No | AC64: No | AD64: No | AE64: No | AF64: No | AG64: No | AH64: Yes | AI64: Clean | AJ64: 30 Oct 2024 | AK64: 02-11-2024 | AL64: Sneha Kapoor | AM64: Home Office | AN64: North | AO64: Rajasthan | AP64: Jaipur | AQ64: Technology | AR64: Phones | AS64: Standard Class | AT64: 0.2 | AU64: Paid | AV64: Completed
A65: ORD-2024-10064 | B65: 45316 | C65: 45323 | D65: CUST-5382 | E65: Sneha Kapoor | F65: Home Office | G65: North | H65: Haryana | I65: Gurugram | J65: Office Supplies | K65: Binders | M65: Same Day | N65: 2 | O65: 2832.77 | P65: 0.15 | Q65: 0.15 | R65: 4815.71 | S65: 3027.75 | T65: 4815.709 | U65: 1787.959 | V65: 0.37127638 | W65: 7 | X65: January | Y65: 2024 | Z65: Paid | AA65: Completed | AB65: No | AC65: No | AD65: No | AE65: No | AF65: No | AG65: No | AH65: Yes | AI65: Clean | AJ65: 2024-01-25 | AK65: 01-02-2024 | AL65: Sneha Kapoor | AM65: Home Office | AN65: North | AO65: Haryana | AP65: Gurugram | AQ65: Office Supplies | AR65: Binders | AS65: Same Day | AT65: 0.15 | AU65: Paid | AV65: Completed
A66: ORD-2024-10065 | B66: 45649 | C66: 45655 | D66: CUST-2749 | E66: Aarav Sharma | F66: Corporate | G66: East | H66: Jharkhand | I66: Ranchi | J66: Office Supplies | K66: Paper | M66: First Class | N66: 7 | O66: 447.84 | P66: 0 | Q66: 0 | R66: 3134.88 | S66: 2367.63 | T66: 3134.88 | U66: 767.25 | V66: 0.24474621 | W66: 6 | X66: December | Y66: 2024 | Z66: Refunded | AA66: Returned | AB66: No | AC66: No | AD66: No | AE66: No | AF66: No | AG66: No | AH66: No | AI66: Clean | AJ66: 2024-12-23 | AK66: 12/29/2024 | AL66: Aarav Sharma | AM66: Corporate | AN66: East | AO66: Jharkhand | AP66: Ranchi | AQ66: Office Supplies | AR66: Paper | AS66: First Class | AT66: 0 | AU66: Refunded | AV66: Returned
A67: ORD-2024-10066 | B67: 45404 | C67: 45409 | D67: CUST-2463 | E67: Mira Das | F67: Home Office | G67: West | H67: Maharashtra | I67: Mumbai | J67: Office Supplies | K67: Paper | M67: Second Class | N67: 1 | O67: 4280.19 | P67: 0.05 | Q67: 0.05 | R67: 4066.18 | S67: 2628.92 | T67: 4066.1805 | U67: 1437.2605 | V67: 0.35346697 | W67: 5 | X67: April | Y67: 2024 | Z67: Paid | AA67: Completed | AB67: No | AC67: No | AD67: No | AE67: No | AF67: No | AG67: No | AH67: Yes | AI67: Clean | AJ67: 22 Apr 2024 | AK67: 2024-04-27 | AL67: Mira Das | AM67: Home Office | AN67: West | AO67: Maharashtra | AP67: Mumbai | AQ67: Office Supplies | AR67: Paper | AS67: Second Class | AT67: 0.05 | AU67: Paid | AV67: Completed
A68: ORD-2025-10067 | B68: 45897 | C68: 45901 | D68: CUST-1504 | E68: Karan Malhotra | F68: Small Business | G68: South | H68: Tamil Nadu | I68: Chennai | J68: Technology | K68: Accessories | M68: Same Day | N68: 7 | O68: 1057.46 | P68: 0.05 | Q68: 0.05 | R68: 7032.11 | S68: 4610.34 | T68: 7032.109 | U68: 2421.769 | V68: 0.3443873 | W68: 4 | X68: August | Y68: 2025 | Z68: Paid | AA68: Completed | AB68: No | AC68: No | AD68: No | AE68: No | AF68: No | AG68: No | AH68: Yes | AI68: Clean | AJ68: 08/28/2025 | AK68: 01 Sep 2025 | AL68: Karan Malhotra | AM68: Small Business | AN68: South | AO68: Tamil Nadu | AP68: Chennai | AQ68: Technology | AR68: Accessories | AS68: Same Day | AT68: 0.05 | AU68: Paid | AV68: Completed
A69: ORD-2025-10068 | B69: 45691 | C69: 45695 | D69: CUST-8282 | E69: Kabir Singh | F69: Consumer | G69: North | H69: Haryana | I69: Gurugram | J69: Office Supplies | K69: Paper | M69: First Class | N69: 7 | O69: 3609.34 | P69: 0.05 | Q69: 0.05 | R69: 24002.11 | S69: 18707.57 | T69: 24002.111 | U69: 5294.541 | V69: 0.22058647 | W69: 4 | X69: February | Y69: 2025 | Z69: Paid | AA69: Completed | AB69: No | AC69: No | AD69: No | AE69: No | AF69: No | AG69: No | AH69: Yes | AI69: Clean | AJ69: 03 Feb 2025 | AK69: 07-02-2025 | AL69: Kabir Singh | AM69: Consumer | AN69: North | AO69: Haryana | AP69: Gurugram | AQ69: Office Supplies | AR69: Paper | AS69: First Class | AT69: 0.05 | AU69: Paid | AV69: Completed
A70: ORD-2024-10069 | B70: 45606 | C70: 45609 | D70: CUST-6054 | E70: Isha Nair | F70: Corporate | G70: East | H70: Jharkhand | I70: Ranchi | J70: Office Supplies | K70: Storage | M70: Second Class | N70: 9 | O70: 2211.12 | P70: 0 | Q70: 0 | R70: 19900.08 | S70: 10962.66 | T70: 19900.08 | U70: 8937.42 | V70: 0.44911478 | W70: 3 | X70: November | Y70: 2024 | Z70: Failed | AA70: Returned | AB70: No | AC70: No | AD70: No | AE70: No | AF70: No | AG70: No | AH70: No | AI70: Clean | AJ70: 11/10/2024 | AK70: 13 Nov 2024 | AL70: Isha Nair | AM70: Corporate | AN70: East | AO70: Jharkhand | AP70: Ranchi | AQ70: Office Supplies | AR70: Storage | AS70: Second Class | AT70: 0 | AU70: Failed | AV70: Returned
A71: ORD-2024-10070 | B71: 45391 | C71: 45396 | D71: CUST-5979 | E71: Neha Gupta | F71: Small Business | G71: West | H71: Gujarat | I71: Ahmedabad | J71: Technology | K71: Machines | M71: Same Day | N71: 7 | O71: 3417.09 | P71: 0.1 | Q71: 0.1 | R71: 21527.67 | S71: 18287.58 | T71: 21527.667 | U71: 3240.087 | V71: 0.15050804 | W71: 5 | X71: April | Y71: 2024 | Z71: Refunded | AA71: Returned | AB71: No | AC71: No | AD71: No | AE71: No | AF71: No | AG71: No | AH71: No | AI71: Clean | AJ71: 09 Apr 2024 | AK71: 04/14/2024 | AL71: Neha Gupta | AM71: Small Business | AN71: West | AO71: Gujarat | AP71: Ahmedabad | AQ71: Technology | AR71: Machines | AS71: Same Day | AT71: 0.1 | AU71: Refunded | AV71: Returned
A72: ORD-2025-10071 | B72: 45891 | C72: 45896 | D72: CUST-5582 | E72: Karan Malhotra | F72: Corporate | G72: South | H72: Andhra Pradesh | I72: Vijayawada | J72: Technology | K72: Phones | M72: First Class | N72: 2 | O72: 905.87 | P72: 0.15 | Q72: 0.15 | R72: 1539.98 | S72: 1070.2 | T72: 1539.979 | U72: 469.779 | V72: 0.30505546 | W72: 5 | X72: August | Y72: 2025 | Z72: Paid | AA72: Completed | AB72: No | AC72: No | AD72: No | AE72: No | AF72: No | AG72: No | AH72: Yes | AI72: Clean | AJ72: 2025-08-22 | AK72: 27 Aug 2025 | AL72: Karan Malhotra | AM72: Corporate | AN72: South | AO72: Andhra Pradesh | AP72: Vijayawada | AQ72: Technology | AR72: Phones | AS72: First Class | AT72: 0.15 | AU72: Paid | AV72: Completed
... A99: ORD-2025-10098 | B99: 45877 | C99: 45880 | D99: CUST-8111 | E99: Diya Patel | F99: Small Business | G99: West | H99: Gujarat | I99: Ahmedabad | J99: Office Supplies | K99: Storage | M99: Same Day | N99: 5 | O99: 3602.36 | P99: 0.2 | Q99: 0.2 | R99: 14409.44 | S99: 8809.97 | T99: 14409.44 | U99: 5599.47 | V99: 0.38859734 | W99: 3 | X99: August | Y99: 2025 | Z99: Pending | AA99: Returned | AB99: No | AC99: No | AD99: No | AE99: No | AF99: No | AG99: No | AH99: No | AI99: Clean | AJ99: 08 Aug 2025 | AK99: 2025-08-11 | AL99: Diya Patel | AM99: Small Business | AN99: West | AO99: Gujarat | AP99: Ahmedabad | AQ99: Office Supplies | AR99: Storage | AS99: Same Day | AT99: 0.2 | AU99: Pending | AV99: Returned
A100: ORD-2024-10099 | B100: 45317 | C100: 45323 | D100: CUST-5434 | E100: Rohan Mehta | F100: Home Office | G100: South | H100: Kerala | I100: Kochi | J100: Technology | K100: Copiers | M100: Unknown | N100: 8 | O100: 2108.93 | P100: 0.1 | Q100: 0.1 | R100: 15184.3 | S100: 11270.74 | T100: 15184.296 | U100: 3913.556 | V100: 0.25773707 | W100: 6 | X100: January | Y100: 2024 | Z100: Paid | AA100: Completed | AB100: No | AC100: Yes | AD100: No | AE100: No | AF100: No | AG100: No | AH100: Yes | AI100: Warning | AJ100: 2024-01-26 | AK100: 02/01/2024 | AL100: Rohan Mehta | AM100: Home Office | AN100: South | AO100: Kerala | AP100: Kochi | AQ100: Technology | AR100: Copiers | AT100: 0.1 | AU100: Paid | AV100: Completed
A101: ORD-2025-10100 | B101: 45668 | C101: 45668 | D101: CUST-3865 | E101: Aditi Sen | F101: Small Business | G101: West | H101: Rajasthan | I101: Udaipur | J101: Technology | K101: Accessories | M101: Same Day | N101: 3 | O101: 2165.29 | P101: 0 | Q101: 0 | R101: 6495.87 | S101: 4700.89 | T101: 6495.87 | U101: 1794.98 | V101: 0.27632634 | W101: 0 | X101: January | Y101: 2025 | Z101: Paid | AA101: Completed | AB101: No | AC101: No | AD101: No | AE101: No | AF101: No | AG101: No | AH101: Yes | AI101: Clean | AJ101: 11-01-2025 | AK101: 11-01-2025 | AL101: Aditi Sen | AM101: Small Business | AN101: West | AO101: Rajasthan | AP101: Udaipur | AQ101: Technology | AR101: Accessories | AS101: Same Day | AT101: 0 | AU101: Paid | AV101: Completed
A102: ORD-2025-10101 | B102: 45912 | C102: 45918 | D102: CUST-6015 | E102: Aarav Sharma | F102: Home Office | G102: South | H102: Kerala | I102: Kochi | J102: Office Supplies | K102: Storage | M102: Standard Class | N102: 6 | O102: 1673.8 | P102: 0.05 | Q102: 0.05 | R102: 9540.66 | S102: 5561.49 | T102: 9540.66 | U102: 3979.17 | V102: 0.41707492 | W102: 6 | X102: September | Y102: 2025 | Z102: Paid | AA102: Completed | AB102: No | AC102: No | AD102: No | AE102: No | AF102: No | AG102: No | AH102: Yes | AI102: Clean | AJ102: 12 Sep 2025 | AK102: 18 Sep 2025 | AL102: Aarav Sharma | AM102: Home Office | AN102: South | AO102: Kerala | AP102: Kochi | AQ102: Office Supplies | AR102: Storage | AS102: Standard Class | AT102: 0.05 | AU102: Paid | AV102: Completed
A103: ORD-2024-10102 | B103: 45465 | C103: 45469 | D103: CUST-7909 | E103: Rohan Mehta | F103: Home Office | G103: East | H103: Bihar | I103: Patna | J103: Furniture | K103: Furnishings | M103: First Class | N103: 5 | O103: 4396.52 | P103: 0.25 | Q103: 0.25 | R103: 16486.95 | S103: 12054.14 | T103: 16486.95 | U103: 4432.81 | V103: 0.2688678 | W103: 4 | X103: June | Y103: 2024 | Z103: Paid | AA103: Completed | AB103: No | AC103: No | AD103: No | AE103: No | AF103: No | AG103: No | AH103: Yes | AI103: Clean | AJ103: 06/22/2024 | AK103: 26-06-2024 | AL103: Rohan Mehta | AM103: Home Office | AN103: East | AO103: Bihar | AP103: Patna | AQ103: Furniture | AR103: Furnishings | AS103: First Class | AT103: 0.25 | AU103: Paid | AV103: Completed
A104: ORD-2025-10103 | B104: 45850 | C104: 45854 | D104: CUST-9603 | E104: Vikram Iyer | F104: Consumer | G104: South | H104: Karnataka | I104: Bengaluru | J104: Furniture | K104: Chairs | M104: First Class | N104: 4 | O104: 2865.71 | P104: 0 | Q104: 0 | R104: 11462.84 | S104: 8979.78 | T104: 11462.84 | U104: 2483.06 | V104: 0.21661822 | W104: 4 | X104: July | Y104: 2025 | Z104: Refunded | AA104: Cancelled | AB104: No | AC104: No | AD104: No | AE104: No | AF104: No | AG104: No | AH104: No | AI104: Clean | AJ104: 12 Jul 2025 | AK104: 2025-07-16 | AL104: Vikram Iyer | AM104: Consumer | AN104: South | AO104: Karnataka | AP104: Bengaluru | AQ104: Furniture | AR104: Chairs | AS104: First Class | AT104: 0 | AU104: Refunded | AV104: Cancelled
A105: ORD-2025-10104 | B105: 45779 | C105: 45787 | D105: CUST-6263 | E105: Kabir Singh | F105: Corporate | G105: West | H105: Maharashtra | I105: Mumbai | J105: Furniture | K105: Tables | M105: First Class | N105: 4 | O105: 2440.34 | P105: 0.2 | Q105: 0.2 | R105: 7809.09 | S105: 6657.75 | T105: 7809.088 | U105: 1151.338 | V105: 0.14743565 | W105: 8 | X105: May | Y105: 2025 | Z105: Paid | AA105: Completed | AB105: No | AC105: No | AD105: No | AE105: No | AF105: No | AG105: No | AH105: Yes | AI105: Clean | AJ105: 05/02/2025 | AK105: 05/10/2025 | AL105: Kabir Singh | AM105: Corporate | AN105: West | AO105: Maharashtra | AP105: Mumbai | AQ105: Furniture | AR105: Tables | AS105: First Class | AT105: 0.2 | AU105: Paid | AV105: Completed
A106: ORD-2025-10105 | B106: 45689 | C106: 45696 | D106: CUST-1576 | E106: Ananya Rao | F106: Consumer | G106: South | H106: Karnataka | I106: Bengaluru | J106: Office Supplies | K106: Labels | M106: Same Day | N106: 5 | O106: 2112.54 | P106: 0.25 | Q106: 0.25 | R106: 8260.46 | S106: 5619.95 | T106: 7922.025 | U106: 2302.075 | V106: 0.29059174 | W106: 7 | X106: February | Y106: 2025 | Z106: Paid | AA106: Cancelled | AB106: No | AC106: No | AD106: No | AE106: No | AF106: No | AG106: No | AH106: No | AI106: Clean | AJ106: 2025-02-01 | AK106: 02/08/2025 | AL106: Ananya Rao | AM106: Consumer | AN106: South | AO106: Karnataka | AP106: Bengaluru | AQ106: Office Supplies | AR106: Labels | AS106: Same Day | AT106: 0.25 | AU106: Paid | AV106: Cancelled
A107: ORD-2024-10106 | B107: 45467 | C107: 45472 | D107: CUST-6540 | E107: Mira Das | F107: Home Office | G107: East | H107: West Bengal | I107: Kolkata | J107: Furniture | K107: Tables | M107: Second Class | N107: 2 | O107: 685 | P107: 0.1 | Q107: 0.1 | R107: 1233 | S107: 1006.9 | T107: 1233 | U107: 226.1 | V107: 0.18337388 | W107: 5 | X107: June | Y107: 2024 | Z107: Paid | AA107: Completed | AB107: No | AC107: No | AD107: No | AE107: No | AF107: No | AG107: No | AH107: Yes | AI107: Clean | AJ107: 06/24/2024 | AK107: 29-06-2024 | AL107: Mira Das | AM107: Home Office | AN107: East | AO107: West Bengal | AP107: Kolkata | AQ107: Furniture | AR107: Tables | AS107: Second Class | AT107: 0.1 | AU107: Paid | AV107: Completed
A108: ORD-2024-10107 | B108: 45342 | C108: 45350 | D108: CUST-4008 | E108: Arjun Bose | F108: Home Office | G108: East | H108: West Bengal | I108: Kolkata | J108: Office Supplies | K108: Paper | M108: Standard Class | N108: 2 | O108: 4004.04 | Q108: 0 | R108: 7207.27 | S108: 5709.39 | T108: 8008.08 | U108: 2298.69 | V108: 0.28704633 | W108: 8 | X108: February | Y108: 2024 | Z108: Paid | AA108: Cancelled | AB108: No | AC108: No | AD108: Yes | AE108: No | AF108: No | AG108: No | AH108: No | AI108: Warning | AJ108: 20-02-2024 | AK108: 28 Feb 2024 | AL108: Arjun Bose | AM108: Home Office | AN108: East | AO108: West Bengal | AP108: Kolkata | AQ108: Office Supplies | AR108: Paper | AS108: Standard Class | AU108: Paid | AV108: Cancelled
A109: ORD-2024-10108 | B109: 45594 | C109: 45600 | D109: CUST-6604 | E109: Rohan Mehta | F109: Home Office | G109: East | H109: West Bengal | I109: Kolkata | J109: Furniture | K109: Furnishings | M109: First Class | N109: 3 | O109: 4302.89 | P109: 0.05 | Q109: 0.05 | R109: 12263.24 | S109: 8925.57 | T109: 12263.237 | U109: 3337.6665 | V109: 0.27216849 | W109: 6 | X109: October | Y109: 2024 | Z109: Paid | AA109: Completed | AB109: No | AC109: No | AD109: No | AE109: No | AF109: No | AG109: No | AH109: Yes | AI109: Clean | AJ109: 29 Oct 2024 | AK109: 2024-11-04 | AL109: Rohan Mehta | AM109: Home Office | AN109: East | AO109: West Bengal | AP109: Kolkata | AQ109: Furniture | AR109: Furnishings | AS109: First Class | AT109: 0.05 | AU109: Paid | AV109: Completed
A110: ORD-2024-10109 | B110: 45519 | C110: 45527 | D110: CUST-4337 | E110: Aditi Sen | F110: Small Business | G110: East | H110: Odisha | I110: Bhubaneswar | J110: Furniture | K110: Bookcases | M110: Same Day | N110: 2 | O110: 537.54 | P110: 0.25 | Q110: 0.25 | R110: 806.31 | S110: 498.5 | T110: 806.31 | U110: 307.81 | V110: 0.38175144 | W110: 8 | X110: August | Y110: 2024 | Z110: Paid | AA110: Completed | AB110: No | AC110: No | AD110: No | AE110: No | AF110: No | AG110: No | AH110: Yes | AI110: Clean | AJ110: 15 Aug 2024 | AK110: 08/23/2024 | AL110: Aditi Sen | AM110: Small Business | AN110: East | AO110: Odisha | AP110: Bhubaneswar | AQ110: Furniture | AR110: Bookcases | AS110: Same Day | AT110: 0.25 | AU110: Paid | AV110: Completed
A111: ORD-2025-10110 | B111: 45892 | C111: 45896 | D111: CUST-3740 | E111: Sneha Kapoor | F111: Consumer | G111: North | H111: Delhi | I111: New Delhi | J111: Office Supplies | K111: Binders | M111: Second Class | N111: 1 | O111: 2788.62 | P111: 0.25 | Q111: 0.25 | R111: 2091.47 | S111: 1317.22 | T111: 2091.465 | U111: 774.245 | V111: 0.37019266 | W111: 4 | X111: August | Y111: 2025 | Z111: Paid | AA111: Completed | AB111: No | AC111: No | AD111: No | AE111: No | AF111: No | AG111: No | AH111: Yes | AI111: Clean | AJ111: 23-08-2025 | AK111: 08/27/2025 | AL111: Sneha Kapoor | AM111: Consumer | AN111: North | AO111: Delhi | AP111: New Delhi | AQ111: Office Supplies | AR111: Binders | AS111: Second Class | AT111: 0.25 | AU111: Paid | AV111: Completed
A112: ORD-2024-10111 | B112: 45583 | C112: 45589 | D112: CUST-7128 | E112: Vikram Iyer | F112: Corporate | G112: South | H112: Kerala | I112: Kochi | J112: Office Supplies | K112: Labels | M112: First Class | N112: 2 | O112: 2250.47 | P112: 0 | Q112: 0 | R112: 4500.94 | S112: 2607.73 | T112: 4500.94 | U112: 1893.21 | V112: 0.42062547 | W112: 6 | X112: October | Y112: 2024 | Z112: Refunded | AA112: Cancelled | AB112: No | AC112: No | AD112: No | AE112: No | AF112: No | AG112: No | AH112: No | AI112: Clean | AJ112: 10/18/2024 | AK112: 2024-10-24 | AL112: Vikram Iyer | AM112: Corporate | AN112: South | AO112: Kerala | AP112: Kochi | AQ112: Office Supplies | AR112: Labels | AS112: First Class | AT112: 0 | AU112: Refunded | AV112: Cancelled
A113: ORD-2025-10112 | B113: 45835 | C113: 45838 | D113: CUST-4743 | E113: Neha Gupta | F113: Corporate | G113: East | H113: Bihar | I113: Patna | J113: Technology | K113: Accessories | M113: First Class | N113: 1 | O113: 1708.44 | P113: 0.05 | Q113: 0.05 | R113: 1623.02 | S113: 1077.46 | T113: 1623.018 | U113: 545.558 | V113: 0.33613798 | W113: 3 | X113: June | Y113: 2025 | Z113: Pending | AA113: Cancelled | AB113: No | AC113: No | AD113: No | AE113: No | AF113: No | AG113: No | AH113: No | AI113: Clean | AJ113: 06/27/2025 | AK113: 2025-06-30 | AL113: Neha Gupta | AM113: Corporate | AN113: East | AO113: Bihar | AP113: Patna | AQ113: Technology | AR113: Accessories | AS113: First Class | AT113: 0.05 | AU113: Pending | AV113: Cancelled
A114: ORD-2024-10113 | B114: 45301 | C114: 45305 | D114: CUST-5213 | E114: Sneha Kapoor | F114: Consumer | G114: Unknown | H114: Gujarat | I114: Ahmedabad | J114: Technology | K114: Accessories | M114: Standard Class | N114: 3 | O114: 3829.48 | P114: 0.05 | Q114: 0.05 | R114: 10914.02 | S114: 6548.74 | T114: 10914.018 | U114: 4365.278 | V114: 0.39996984 | W114: 4 | X114: January | Y114: 2024 | Z114: Paid | AA114: Completed | AB114: Yes | AC114: No | AD114: No | AE114: No | AF114: No | AG114: No | AH114: Yes | AI114: Warning | AJ114: 10 Jan 2024 | AK114: 14-01-2024 | AL114: Sneha Kapoor | AM114: Consumer | AO114: Gujarat | AP114: Ahmedabad | AQ114: Technology | AR114: Accessories | AS114: Standard Class | AT114: 0.05 | AU114: Paid | AV114: Completed
A115: ORD-2024-10114 | B115: 45334 | C115: 45334 | D115: CUST-4989 | E115: Isha Nair | F115: Home Office | G115: South | H115: Tamil Nadu | I115: Chennai | J115: Furniture | K115: Tables | M115: Standard Class | N115: 3 | O115: 1089.15 | P115: 0.25 | Q115: 0.25 | R115: 2450.59 | S115: 1639.89 | T115: 2450.5875 | U115: 810.6975 | V115: 0.33081761 | W115: 0 | X115: February | Y115: 2024 | Z115: Paid | AA115: Completed | AB115: No | AC115: No | AD115: No | AE115: No | AF115: No | AG115: No | AH115: Yes | AI115: Clean | AJ115: 12-02-2024 | AK115: 12-02-2024 | AL115: Isha Nair | AM115: Home Office | AN115: South | AO115: Tamil Nadu | AP115: Chennai | AQ115: Furniture | AR115: Tables | AS115: Standard Class | AT115: 0.25 | AU115: Paid | AV115: Completed
A116: ORD-2024-10115 | B116: 45560 | C116: 45565 | D116: CUST-2927 | E116: Neha Gupta | F116: Small Business | G116: North | H116: Rajasthan | I116: Jaipur | J116: Technology | K116: Accessories | M116: Second Class | N116: 1 | O116: 4388.4 | P116: 0.1 | Q116: 0.1 | R116: 3949.56 | S116: 3186.73 | T116: 3949.56 | U116: 762.83 | V116: 0.19314303 | W116: 5 | X116: September | Y116: 2024 | Z116: Pending | AA116: Cancelled | AB116: No | AC116: No | AD116: No | AE116: No | AF116: No | AG116: No | AH116: No | AI116: Clean | AJ116: 2024-09-25 | AK116: 30 Sep 2024 | AL116: Neha Gupta | AM116: Small Business | AN116: North | AO116: Rajasthan | AP116: Jaipur | AQ116: Technology | AR116: Accessories | AS116: Second Class | AT116: 0.1 | AU116: Pending | AV116: Cancelled
A117: ORD-2024-10116 | B117: 45653 | C117: 45658 | D117: CUST-7764 | E117: Kabir Singh | F117: Corporate | G117: South | H117: Tamil Nadu | I117: Chennai | J117: Office Supplies | K117: Binders | M117: Same Day | N117: 2 | O117: 446.34 | P117: 0.15 | Q117: 0.15 | R117: 758.78 | S117: 490.74 | T117: 758.778 | U117: 268.038 | V117: 0.35324957 | W117: 5 | X117: December | Y117: 2024 | Z117: Paid | AA117: Cancelled | AB117: No | AC117: No | AD117: No | AE117: No | AF117: No | AG117: No | AH117: No | AI117: Clean | AJ117: 2024-12-27 | AK117: 01-01-2025 | AL117: Kabir Singh | AM117: Corporate | AN117: South | AO117: Tamil Nadu | AP117: Chennai | AQ117: Office Supplies | AR117: Binders | AS117: Same Day | AT117: 0.15 | AU117: Paid | AV117: Cancelled
A118: ORD-2025-10117 | B118: 45703 | C118: 45707 | D118: CUST-3632 | E118: Ananya Rao | F118: Small Business | G118: Unknown | H118: Madhya Pradesh | I118: Indore | J118: Office Supplies | K118: Binders | M118: First Class | N118: 9 | O118: 531.99 | P118: 0.25 | Q118: 0.25 | R118: 3590.93 | S118: 3061.39 | T118: 3590.9325 | U118: 529.5425 | V118: 0.14746657 | W118: 4 | X118: February | Y118: 2025 | Z118: Failed | AA118: Cancelled | AB118: Yes | AC118: No | AD118: No | AE118: No | AF118: No | AG118: No | AH118: No | AI118: Warning | AJ118: 2025-02-15 | AK118: 19 Feb 2025 | AL118: Ananya Rao | AM118: Small Business | AO118: Madhya Pradesh | AP118: Indore | AQ118: Office Supplies | AR118: Binders | AS118: First Class | AT118: 0.25 | AU118: Failed | AV118: Cancelled
A119: ORD-2024-10118 | B119: 45337 | C119: 45339 | D119: CUST-9608 | E119: Mira Das | F119: Home Office | G119: South | H119: Tamil Nadu | I119: Chennai | J119: Technology | K119: Machines | M119: Standard Class | N119: 9 | O119: 3324.55 | P119: 0.7 | Q119: 0 | R119: 25432.81 | S119: 20370.16 | T119: 29920.95 | U119: 9550.79 | V119: 0.31920076 | W119: 2 | X119: February | Y119: 2024 | Z119: Paid | AA119: Completed | AB119: No | AC119: No | AD119: No | AE119: No | AF119: Yes | AG119: No | AH119: Yes | AI119: Invalid | AJ119: 2024-02-15 | AK119: 17 Feb 2024 | AL119: Mira Das | AM119: Home Office | AN119: South | AO119: Tamil Nadu | AP119: Chennai | AQ119: Technology | AR119: Machines | AS119: Standard Class | AT119: 70% | AU119: Paid | AV119: Completed
A120: ORD-2024-10119 | B120: 45453 | C120: 45461 | D120: CUST-9135 | E120: Vikram Iyer | F120: Home Office | G120: South | H120: Andhra Pradesh | I120: Vijayawada | J120: Technology | K120: Copiers | M120: Same Day | N120: 5 | O120: 1580.27 | P120: 0.2 | Q120: 0.2 | R120: 6321.08 | S120: 4407.22 | T120: 6321.08 | U120: 1913.86 | V120: 0.30277421 | W120: 8 | X120: June | Y120: 2024 | Z120: Paid | AA120: Completed | AB120: No | AC120: No | AD120: No | AE120: No | AF120: No | AG120: No | AH120: Yes | AI120: Clean | AJ120: 06/10/2024 | AK120: 2024-06-18 | AL120: Vikram Iyer | AM120: Home Office | AN120: South | AO120: Andhra Pradesh | AP120: Vijayawada | AQ120: Technology | AR120: Copiers | AS120: Same Day | AT120: 0.2 | AU120: Paid | AV120: Completed
A121: ORD-2024-10120 | B121: 45455 | C121: 45462 | D121: CUST-7861 | E121: Aditi Sen | F121: Small Business | G121: South | H121: Kerala | I121: Kochi | J121: Furniture | K121: Chairs | M121: Standard Class | N121: 8 | O121: 314.05 | P121: 0.25 | Q121: 0.25 | R121: 1884.3 | S121: 1517.69 | T121: 1884.3 | U121: 366.61 | V121: 0.19456031 | W121: 7 | X121: June | Y121: 2024 | Z121: Refunded | AA121: Returned | AB121: No | AC121: No | AD121: No | AE121: No | AF121: No | AG121: No | AH121: No | AI121: Clean | AJ121: 12 Jun 2024 | AK121: 19 Jun 2024 | AL121: Aditi Sen | AM121: Small Business | AN121: South | AO121: Kerala | AP121: Kochi | AQ121: Furniture | AR121: Chairs | AS121: Standard Class | AT121: 0.25 | AU121: Refunded | AV121: Returned
A122: ORD-2024-10121 | B122: 45514 | C122: 45522 | D122: CUST-6096 | E122: Sneha Kapoor | F122: Small Business | G122: East | H122: Bihar | I122: Patna | J122: Technology | K122: Phones | M122: Standard Class | N122: 1 | O122: 1823.67 | P122: 0.2 | Q122: 0.2 | R122: 1458.94 | S122: 893.2 | T122: 1458.936 | U122: 565.736 | V122: 0.38777301 | W122: 8 | X122: August | Y122: 2024 | Z122: Paid | AA122: Returned | AB122: No | AC122: No | AD122: No | AE122: No | AF122: No | AG122: No | AH122: No | AI122: Clean | AJ122: 2024-08-10 | AK122: 2024-08-18 | AL122: Sneha Kapoor | AM122: Small Business | AN122: East | AO122: Bihar | AP122: Patna | AQ122: Technology | AR122: Phones | AS122: Standard Class | AT122: 0.2 | AU122: Paid | AV122: Returned
A123: ORD-2025-10122 | B123: 45891 | C123: 45895 | D123: CUST-2044 | E123: Kabir Singh | F123: Small Business | G123: South | H123: Andhra Pradesh | I123: Vijayawada | J123: Technology | K123: Machines | M123: Second Class | N123: 5 | O123: 3482.92 | P123: 0 | Q123: 0 | R123: 17414.6 | S123: 11760.91 | T123: 17414.6 | U123: 5653.69 | V123: 0.3246523 | W123: 4 | X123: August | Y123: 2025 | Z123: Refunded | AA123: Cancelled | AB123: No | AC123: No | AD123: No | AE123: No | AF123: No | AG123: No | AH123: No | AI123: Clean | AJ123: 08/22/2025 | AK123: 08/26/2025 | AL123: Kabir Singh | AM123: Small Business | AN123: South | AO123: Andhra Pradesh | AP123: Vijayawada | AQ123: Technology | AR123: Machines | AS123: Second Class | AT123: 0 | AU123: Refunded | AV123: Cancelled
A124: ORD-2024-10123 | B124: 45626 | C124: 45630 | D124: CUST-1721 | E124: Ananya Rao | F124: Small Business | G124: East | H124: Assam | I124: Guwahati | J124: Furniture | K124: Chairs | M124: Second Class | N124: 3 | O124: 170.35 | P124: 0 | Q124: 0 | R124: 511.05 | S124: 367.18 | T124: 511.05 | U124: 143.87 | V124: 0.28151844 | W124: 4 | X124: November | Y124: 2024 | Z124: Paid | AA124: Completed | AB124: No | AC124: No | AD124: No | AE124: No | AF124: No | AG124: No | AH124: Yes | AI124: Clean | AJ124: 11/30/2024 | AK124: 04-12-2024 | AL124: Ananya Rao | AM124: Small Business | AN124: East | AO124: Assam | AP124: Guwahati | AQ124: Furniture | AR124: Chairs | AS124: Second Class | AT124: 0 | AU124: Paid | AV124: Completed
A125: ORD-2024-10124 | B125: 45436 | C125: 45437 | D125: CUST-1007 | E125: Sneha Kapoor | F125: Small Business | G125: North | H125: Punjab | I125: Ludhiana | J125: Technology | K125: Copiers | M125: Same Day | N125: 1 | O125: 634.13 | P125: 0 | Q125: 0 | R125: 634.13 | S125: 453.35 | T125: 634.13 | U125: 180.78 | V125: 0.2850835 | W125: 1 | X125: May | Y125: 2024 | Z125: Refunded | AA125: Cancelled | AB125: No | AC125: No | AD125: No | AE125: No | AF125: No | AG125: Yes | AH125: No | AI125: Invalid | AJ125: 05/24/2024 | AK125: 25 May 2024 | AL125: Sneha Kapoor | AM125: Small Business | AN125: NORTH | AO125: Punjab | AP125: Ludhiana | AQ125: Technology | AR125: Copiers | AS125: Same Day | AT125: 0 | AU125: Refunded | AV125: Cancelled
A126: ORD-2024-10125 | B126: 45494 | C126: 45497 | D126: CUST-4450 | E126: Isha Nair | F126: Corporate | G126: South | H126: Karnataka | I126: Bengaluru | J126: Technology | K126: Copiers | M126: Standard Class | N126: 9 | O126: 465.06 | P126: -0.15 | Q126: 0 | R126: 4185.54 | S126: 3443.74 | T126: 4185.54 | U126: 741.8 | V126: 0.17722922 | W126: 3 | X126: July | Y126: 2024 | Z126: Paid | AA126: Completed | AB126: No | AC126: No | AD126: No | AE126: No | AF126: Yes | AG126: No | AH126: Yes | AI126: Invalid | AJ126: 21 Jul 2024 | AK126: 07/24/2024 | AL126: Isha Nair | AM126: Corporate | AN126: South | AO126: Karnataka | AP126: Bengaluru | AQ126: Technology | AR126: Copiers | AS126: Standard Class | AT126: -0.15 | AU126: Paid | AV126: Completed
A127: ORD-2025-10126 | B127: 45855 | C127: 45856 | D127: CUST-7924 | E127: Neha Gupta | F127: Small Business | G127: West | H127: Rajasthan | I127: Udaipur | J127: Furniture | K127: Tables | M127: Same Day | N127: 6 | O127: 3235.27 | P127: 0.25 | Q127: 0.25 | R127: 14558.72 | S127: 9591.48 | T127: 14558.715 | U127: 4967.235 | V127: 0.34118636 | W127: 1 | X127: July | Y127: 2025 | Z127: Refunded | AA127: Returned | AB127: No | AC127: No | AD127: No | AE127: No | AF127: No | AG127: No | AH127: No | AI127: Clean | AJ127: 2025-07-17 | AK127: 18-07-2025 | AL127: Neha Gupta | AM127: Small Business | AN127: West | AO127: Rajasthan | AP127: Udaipur | AQ127: Furniture | AR127: Tables | AS127: Same Day | AT127: 0.25 | AU127: Refunded | AV127: Returned
A128: ORD-2025-10127 | B128: 45924 | C128: 45926 | D128: CUST-1715 | E128: Priya Menon | F128: Corporate | G128: North | H128: Delhi | I128: New Delhi | J128: Technology | K128: Copiers | M128: Standard Class | N128: 3 | O128: 1593.86 | P128: 0.1 | Q128: 0.1 | R128: 4303.42 | S128: 2568.57 | T128: 4303.422 | U128: 1734.852 | V128: 0.40313313 | W128: 2 | X128: September | Y128: 2025 | Z128: Paid | AA128: Completed | AB128: No | AC128: No | AD128: No | AE128: No | AF128: No | AG128: No | AH128: Yes | AI128: Clean | AJ128: 24-09-2025 | AK128: 26 Sep 2025 | AL128: Priya Menon | AM128: Corporate | AN128: North | AO128: Delhi | AP128: New Delhi | AQ128: Technology | AR128: Copiers | AS128: Standard Class | AT128: 0.1 | AU128: Paid | AV128: Completed
A129: ORD-2025-10128 | B129: 45687 | C129: 45683 | D129: CUST-6802 | E129: Priya Menon | F129: Corporate | G129: West | H129: Madhya Pradesh | I129: Indore | J129: Office Supplies | K129: Storage | M129: Second Class | N129: 2 | O129: 3039.3 | P129: 0.05 | Q129: 0.05 | R129: 5774.67 | S129: 3518.36 | T129: 5774.67 | U129: 2256.31 | V129: 0.39072536 | W129: -4 | X129: January | Y129: 2025 | Z129: Paid | AA129: Completed | AB129: No | AC129: No | AD129: No | AE129: Yes | AF129: No | AG129: No | AH129: Yes | AI129: Invalid | AJ129: 01/30/2025 | AK129: 26-01-2025 | AL129: Priya Menon | AM129: Corporate | AN129: West | AO129: Madhya Pradesh | AP129: Indore | AQ129: Office Supplies | AR129: Storage | AS129: Second Class | AT129: 0.05 | AU129: Paid | AV129: Completed
A130: ORD-2024-10129 | B130: 45639 | C130: 45642 | D130: CUST-9328 | E130: Neha Gupta | F130: Small Business | G130: East | H130: Odisha | I130: Bhubaneswar | J130: Furniture | K130: Furnishings | M130: Standard Class | N130: 5 | O130: 923.45 | P130: 0.05 | Q130: 0.05 | R130: 4386.39 | S130: 3366.88 | T130: 4386.3875 | U130: 1019.5075 | V130: 0.23242532 | W130: 3 | X130: December | Y130: 2024 | Z130: Paid | AA130: Returned | AB130: No | AC130: No | AD130: No | AE130: No | AF130: No | AG130: No | AH130: No | AI130: Clean | AJ130: 13 Dec 2024 | AK130: 16 Dec 2024 | AL130: Neha Gupta | AM130: Small Business | AN130: East | AO130: Odisha | AP130: Bhubaneswar | AQ130: Furniture | AR130: Furnishings | AS130: Standard Class | AT130: 0.05 | AU130: Paid | AV130: Returned
A131: ORD-2024-10130 | B131: 45492 | C131: 45498 | D131: CUST-2588 | E131: Isha Nair | F131: Small Business | G131: West | H131: Goa | I131: Panaji | J131: Office Supplies | K131: Binders | M131: Standard Class | N131: 7 | O131: 2741.29 | P131: 0.05 | Q131: 0.05 | R131: 18229.58 | S131: 15139.15 | T131: 18229.578 | U131: 3090.4285 | V131: 0.16952825 | W131: 6 | X131: July | Y131: 2024 | Z131: Paid | AA131: Completed | AB131: No | AC131: No | AD131: No | AE131: No | AF131: No | AG131: No | AH131: Yes | AI131: Clean | AJ131: 2024-07-19 | AK131: 25-07-2024 | AL131: Isha Nair | AM131: Small Business | AN131: West | AO131: Goa | AP131: Panaji | AQ131: Office Supplies | AR131: Binders | AS131: Standard Class | AT131: 0.05 | AU131: Paid | AV131: Completed
... A135: ORD-2024-10134 | B135: 45639 | C135: 45644 | D135: CUST-9441 | E135: Karan Malhotra | F135: Consumer | G135: West | H135: Goa | I135: Panaji | J135: Technology | K135: Phones | M135: Second Class | N135: 8 | O135: 3372.15 | P135: 0.15 | Q135: 0.15 | R135: 22930.62 | S135: 16875.55 | T135: 22930.62 | U135: 6055.07 | V135: 0.26406046 | W135: 5 | X135: December | Y135: 2024 | Z135: Paid | AA135: Completed | AB135: No | AC135: No | AD135: No | AE135: No | AF135: No | AG135: No | AH135: Yes | AI135: Clean | AJ135: 2024-12-13 | AK135: 12/18/2024 | AL135: Karan Malhotra | AM135: Consumer | AN135: West | AO135: Goa | AP135: Panaji | AQ135: Technology | AR135: Phones | AS135: Second Class | AT135: 0.15 | AU135: Paid | AV135: Completed
A136: ORD-2025-10135 | B136: 45852 | C136: 45852 | D136: CUST-7361 | E136: Vikram Iyer | F136: Home Office | G136: East | H136: West Bengal | I136: Kolkata | J136: Furniture | K136: Bookcases | M136: Unknown | N136: 5 | O136: 383.1 | P136: 0.25 | Q136: 0.25 | R136: 1436.62 | S136: 912.52 | T136: 1436.625 | U136: 524.105 | V136: 0.36481685 | W136: 0 | X136: July | Y136: 2025 | Z136: Pending | AA136: Cancelled | AB136: No | AC136: Yes | AD136: No | AE136: No | AF136: No | AG136: No | AH136: No | AI136: Warning | AJ136: 07/14/2025 | AK136: 2025-07-14 | AL136: Vikram Iyer | AM136: Home Office | AN136: East | AO136: West Bengal | AP136: Kolkata | AQ136: Furniture | AR136: Bookcases | AT136: 0.25 | AU136: Pending | AV136: Cancelled
A137: ORD-2025-10136 | B137: 45893 | C137: 45893 | D137: CUST-1148 | E137: Diya Patel | F137: Small Business | G137: South | H137: Kerala | I137: Kochi | J137: Furniture | K137: Bookcases | M137: Standard Class | N137: 1 | O137: 3424.78 | P137: 0 | Q137: 0 | R137: 3424.78 | S137: 1951.45 | T137: 3424.78 | U137: 1473.33 | V137: 0.43019698 | W137: 0 | X137: August | Y137: 2025 | Z137: Paid | AA137: Completed | AB137: No | AC137: No | AD137: No | AE137: No | AF137: No | AG137: No | AH137: Yes | AI137: Clean | AJ137: 2025-08-24 | AK137: 2025-08-24 | AL137: Diya Patel | AM137: Small Business | AN137: South | AO137: Kerala | AP137: Kochi | AQ137: Furniture | AR137: Bookcases | AS137: Standard Class | AT137: 0 | AU137: Paid | AV137: Completed
A138: ORD-2025-10137 | B138: 45697 | C138: 45703 | D138: CUST-3350 | E138: Mira Das | F138: Home Office | G138: East | H138: Jharkhand | I138: Ranchi | J138: Office Supplies | K138: Binders | M138: Standard Class | N138: 9 | O138: 4330.33 | P138: 0.2 | Q138: 0.2 | R138: 31178.38 | S138: 21421.09 | T138: 31178.376 | U138: 9757.286 | V138: 0.31295042 | W138: 6 | X138: February | Y138: 2025 | Z138: Paid | AA138: Completed | AB138: No | AC138: No | AD138: No | AE138: No | AF138: No | AG138: No | AH138: Yes | AI138: Clean | AJ138: 09-02-2025 | AK138: 15-02-2025 | AL138: Mira Das | AM138: Home Office | AN138: East | AO138: Jharkhand | AP138: Ranchi | AQ138: Office Supplies | AR138: Binders | AS138: Standard Class | AT138: 0.2 | AU138: Paid | AV138: Completed
A139: ORD-2025-10138 | B139: 45666 | C139: 45666 | D139: CUST-7932 | E139: Sneha Kapoor | F139: Small Business | G139: North | H139: Rajasthan | I139: Jaipur | J139: Furniture | K139: Chairs | M139: Same Day | N139: 8 | O139: 2667.07 | P139: 0.1 | Q139: 0.1 | R139: 19202.9 | S139: 15526.62 | T139: 19202.904 | U139: 3676.284 | V139: 0.19144417 | W139: 0 | X139: January | Y139: 2025 | Z139: Paid | AA139: Completed | AB139: No | AC139: No | AD139: No | AE139: No | AF139: No | AG139: No | AH139: Yes | AI139: Clean | AJ139: 01/09/2025 | AK139: 2025-01-09 | AL139: Sneha Kapoor | AM139: Small Business | AN139: North | AO139: Rajasthan | AP139: Jaipur | AQ139: Furniture | AR139: Chairs | AS139: Same Day | AT139: 0.1 | AU139: Paid | AV139: Completed
A140: ORD-2024-10139 | B140: 45311 | C140: 45317 | D140: CUST-7173 | E140: Diya Patel | F140: Home Office | G140: East | H140: Jharkhand | I140: Ranchi | J140: Technology | K140: Machines | M140: Standard Class | N140: 8 | O140: 4003.05 | P140: 0.25 | Q140: 0.25 | R140: 24018.3 | S140: 14070.78 | T140: 24018.3 | U140: 9947.52 | V140: 0.4141642 | W140: 6 | X140: January | Y140: 2024 | Z140: Paid | AA140: Completed | AB140: No | AC140: No | AD140: No | AE140: No | AF140: No | AG140: No | AH140: Yes | AI140: Clean | AJ140: 2024-01-20 | AK140: 26-01-2024 | AL140: Diya Patel | AM140: Home Office | AN140: East | AO140: Jharkhand | AP140: Ranchi | AQ140: Technology | AR140: Machines | AS140: Standard Class | AT140: 0.25 | AU140: Paid | AV140: Completed
A141: ORD-2025-10140 | B141: 45718 | C141: 45723 | D141: CUST-4225 | E141: Neha Gupta | F141: Home Office | G141: South | H141: Karnataka | I141: Bengaluru | J141: Office Supplies | K141: Labels | M141: Standard Class | N141: 8 | O141: 1287.63 | P141: 0 | Q141: 0 | R141: 10301.04 | S141: 6564.06 | T141: 10301.04 | U141: 3736.98 | V141: 0.36277696 | W141: 5 | X141: March | Y141: 2025 | Z141: Paid | AA141: Completed | AB141: No | AC141: No | AD141: No | AE141: No | AF141: No | AG141: No | AH141: Yes | AI141: Clean | AJ141: 03/02/2025 | AK141: 07-03-2025 | AL141: Neha Gupta | AM141: Home Office | AN141: South | AO141: Karnataka | AP141: Bengaluru | AQ141: Office Supplies | AR141: Labels | AS141: Standard Class | AT141: 0 | AU141: Paid | AV141: Completed
A142: ORD-2024-10141 | B142: 45443 | C142: 45444 | D142: CUST-2149 | E142: Mira Das | F142: Corporate | G142: South | H142: Karnataka | I142: Bengaluru | J142: Furniture | K142: Bookcases | M142: Same Day | N142: 3 | O142: 2914.55 | P142: 0 | Q142: 0 | R142: 8743.65 | S142: 6603.76 | T142: 8743.65 | U142: 2139.89 | V142: 0.24473647 | W142: 1 | X142: May | Y142: 2024 | Z142: Paid | AA142: Completed | AB142: No | AC142: No | AD142: No | AE142: No | AF142: No | AG142: No | AH142: Yes | AI142: Clean | AJ142: 31-05-2024 | AK142: 01 Jun 2024 | AL142: Mira Das | AM142: Corporate | AN142: South | AO142: Karnataka | AP142: Bengaluru | AQ142: Furniture | AR142: Bookcases | AS142: Same Day | AT142: 0 | AU142: Paid | AV142: Completed
A143: ORD-2024-10142 | B143: 45374 | C143: 45380 | D143: CUST-3314 | E143: Priya Menon | F143: Corporate | G143: North | H143: Delhi | I143: New Delhi | J143: Furniture | K143: Bookcases | M143: Same Day | N143: 7 | O143: 634.29 | P143: 0.1 | Q143: 0.1 | R143: 3996.03 | S143: 2859.51 | T143: 3996.027 | U143: 1136.517 | V143: 0.28441174 | W143: 6 | X143: March | Y143: 2024 | Z143: Paid | AA143: Returned | AB143: No | AC143: No | AD143: No | AE143: No | AF143: No | AG143: No | AH143: No | AI143: Clean | AJ143: 03/23/2024 | AK143: 2024-03-29 | AL143: Priya Menon | AM143: Corporate | AN143: North | AO143: Delhi | AP143: New Delhi | AQ143: Furniture | AR143: Bookcases | AS143: Same Day | AT143: 0.1 | AU143: Paid | AV143: Returned
A144: ORD-2024-10143 | B144: 45381 | C144: 45377 | D144: CUST-8944 | E144: Aditi Sen | F144: Home Office | G144: North | H144: Rajasthan | I144: Jaipur | J144: Technology | K144: Phones | M144: Second Class | N144: 5 | O144: 907.54 | P144: 0.15 | Q144: 0.15 | R144: 3857.04 | S144: 2769.26 | T144: 3857.045 | U144: 1087.785 | V144: 0.28202549 | W144: -4 | X144: March | Y144: 2024 | Z144: Paid | AA144: Completed | AB144: No | AC144: No | AD144: No | AE144: Yes | AF144: No | AG144: Yes | AH144: Yes | AI144: Invalid | AJ144: 30 Mar 2024 | AK144: 26 Mar 2024 | AL144: Aditi Sen | AM144: Home Office | AN144: North | AO144: Rajasthan | AP144: Jaipur | AQ144: Technology | AR144: Phones | AS144: Second Class | AT144: 0.15 | AU144: Paid | AV144: Completed
A145: ORD-2024-10144 | B145: 45375 | C145: 45377 | D145: CUST-3144 | E145: Priya Menon | F145: Consumer | G145: West | H145: Gujarat | I145: Ahmedabad | J145: Office Supplies | K145: Paper | M145: Second Class | N145: 1 | O145: 3409.5 | P145: 0.1 | Q145: 0.1 | R145: 3068.55 | S145: 1916.16 | T145: 3068.55 | U145: 1152.39 | V145: 0.37554871 | W145: 2 | X145: March | Y145: 2024 | Z145: Paid | AA145: Returned | AB145: No | AC145: No | AD145: No | AE145: No | AF145: No | AG145: No | AH145: No | AI145: Clean | AJ145: 03/24/2024 | AK145: 2024-03-26 | AL145: Priya Menon | AM145: Consumer | AN145: West | AO145: Gujarat | AP145: Ahmedabad | AQ145: Office Supplies | AR145: Paper | AS145: Second Class | AT145: 0.1 | AU145: Paid | AV145: Returned
A146: ORD-2024-10145 | B146: 45450 | C146: 45458 | D146: CUST-6747 | E146: Kabir Singh | F146: Small Business | G146: South | H146: Telangana | I146: Hyderabad | J146: Technology | K146: Accessories | M146: First Class | N146: 7 | O146: 2147.99 | P146: 0.25 | Q146: 0.25 | R146: 11276.95 | S146: 6908.76 | T146: 11276.948 | U146: 4368.1875 | V146: 0.38735549 | W146: 8 | X146: June | Y146: 2024 | Z146: Refunded | AA146: Returned | AB146: No | AC146: No | AD146: No | AE146: No | AF146: No | AG146: No | AH146: No | AI146: Clean | AJ146: 07-06-2024 | AK146: 2024-06-15 | AL146: Kabir Singh | AM146: Small Business | AN146: South | AO146: Telangana | AP146: Hyderabad | AQ146: Technology | AR146: Accessories | AS146: First Class | AT146: 0.25 | AU146: Refunded | AV146: Returned
A147: ORD-2025-10146 | B147: 45758 | C147: 45760 | D147: CUST-6161 | E147: Mira Das | F147: Small Business | G147: West | H147: Goa | I147: Panaji | J147: Office Supplies | K147: Paper | M147: Standard Class | N147: 4 | O147: 4182.15 | P147: 0.1 | Q147: 0.1 | R147: 15055.74 | S147: 9808.83 | T147: 15055.74 | U147: 5246.91 | V147: 0.34849898 | W147: 2 | X147: April | Y147: 2025 | Z147: Paid | AA147: Completed | AB147: No | AC147: No | AD147: No | AE147: No | AF147: No | AG147: No | AH147: Yes | AI147: Clean | AJ147: 11-04-2025 | AK147: 04/13/2025 | AL147: Mira Das | AM147: Small Business | AN147: West | AO147: Goa | AP147: Panaji | AQ147: Office Supplies | AR147: Paper | AS147: Standard Class | AT147: 0.1 | AU147: Paid | AV147: Completed
A148: ORD-2025-10147 | B148: 45868 | C148: 45870 | D148: CUST-1460 | E148: Sneha Kapoor | F148: Small Business | G148: South | H148: Tamil Nadu | I148: Chennai | J148: Office Supplies | K148: Storage | M148: Same Day | N148: 9 | O148: 3165.43 | P148: 0.1 | Q148: 0.1 | R148: 25639.98 | S148: 21635.08 | T148: 25639.983 | U148: 4004.903 | V148: 0.15619757 | W148: 2 | X148: July | Y148: 2025 | Z148: Paid | AA148: Completed | AB148: No | AC148: No | AD148: No | AE148: No | AF148: No | AG148: No | AH148: Yes | AI148: Clean | AJ148: 30 Jul 2025 | AK148: 08/01/2025 | AL148: Sneha Kapoor | AM148: Small Business | AN148: South | AO148: Tamil Nadu | AP148: Chennai | AQ148: Office Supplies | AR148: Storage | AS148: Same Day | AT148: 0.1 | AU148: Paid | AV148: Completed
A149: ORD-2024-10148 | B149: 45649 | C149: 45656 | D149: CUST-2692 | E149: Priya Menon | F149: Home Office | G149: West | H149: Goa | I149: Panaji | J149: Furniture | K149: Furnishings | M149: First Class | N149: 8 | O149: 386.1 | P149: 0.1 | Q149: 0.1 | R149: 2779.92 | S149: 1744.05 | T149: 2779.92 | U149: 1035.87 | V149: 0.37262583 | W149: 7 | X149: December | Y149: 2024 | Z149: Paid | AA149: Completed | AB149: No | AC149: No | AD149: No | AE149: No | AF149: No | AG149: No | AH149: Yes | AI149: Clean | AJ149: 23-12-2024 | AK149: 2024-12-30 | AL149: Priya Menon | AM149: Home Office | AN149: West | AO149: Goa | AP149: Panaji | AQ149: Furniture | AR149: Furnishings | AS149: First Class | AT149: 0.1 | AU149: Paid | AV149: Completed
A150: ORD-2025-10149 | B150: 45697 | C150: 45701 | D150: CUST-2822 | E150: Mira Das | F150: Home Office | G150: West | H150: Madhya Pradesh | I150: Indore | J150: Technology | K150: Phones | M150: Unknown | N150: 8 | O150: 1696.07 | P150: 0.25 | Q150: 0.25 | R150: 10176.42 | S150: 7604.47 | T150: 10176.42 | U150: 2571.95 | V150: 0.25273623 | W150: 4 | X150: February | Y150: 2025 | Z150: Paid | AA150: Completed | AB150: No | AC150: Yes | AD150: No | AE150: No | AF150: No | AG150: No | AH150: Yes | AI150: Warning | AJ150: 09 Feb 2025 | AK150: 13-02-2025 | AL150: Mira Das | AM150: Home Office | AN150: West | AO150: Madhya Pradesh | AP150: Indore | AQ150: Technology | AR150: Phones | AT150: 0.25 | AU150: Paid | AV150: Completed
A151: ORD-2024-10150 | B151: 45321 | C151: 45321 | D151: CUST-5876 | E151: Aarav Sharma | F151: Small Business | G151: West | H151: Rajasthan | I151: Udaipur | J151: Technology | K151: Copiers | M151: Same Day | N151: 7 | O151: 2527.61 | P151: 0.25 | Q151: 0.25 | R151: 13269.95 | S151: 8977.1 | T151: 13269.952 | U151: 4292.8525 | V151: 0.32350172 | W151: 0 | X151: January | Y151: 2024 | Z151: Paid | AA151: Completed | AB151: No | AC151: No | AD151: No | AE151: No | AF151: No | AG151: No | AH151: Yes | AI151: Clean | AJ151: 30-01-2024 | AK151: 30-01-2024 | AL151: Aarav Sharma | AM151: Small Business | AN151: west | AO151: Rajasthan | AP151: Udaipur | AQ151: Technology | AR151: Copiers | AS151: Same Day | AT151: 0.25 | AU151: Paid | AV151: Completed
A152: ORD-2024-10151 | B152: 45355 | C152: 45363 | D152: CUST-4661 | E152: Arjun Bose | F152: Consumer | G152: Unknown | H152: Gujarat | I152: Ahmedabad | J152: Furniture | K152: Bookcases | M152: First Class | N152: 1 | O152: 1554.12 | P152: 0.1 | Q152: 0.1 | R152: 1398.71 | S152: 1056.92 | T152: 1398.708 | U152: 341.788 | V152: 0.24435979 | W152: 8 | X152: March | Y152: 2024 | Z152: Paid | AA152: Completed | AB152: Yes | AC152: No | AD152: No | AE152: No | AF152: No | AG152: No | AH152: Yes | AI152: Warning | AJ152: 04-03-2024 | AK152: 2024-03-12 | AL152: Arjun Bose | AM152: Consumer | AO152: Gujarat | AP152: Ahmedabad | AQ152: Furniture | AR152: Bookcases | AS152: First Class | AT152: 0.1 | AU152: Paid | AV152: Completed
A153: ORD-2024-10152 | B153: 45470 | C153: 45470 | D153: CUST-6011 | E153: Neha Gupta | F153: Home Office | G153: Unknown | H153: Madhya Pradesh | I153: Indore | J153: Technology | K153: Copiers | M153: Standard Class | N153: 2 | O153: 3859.11 | P153: 0 | Q153: 0 | R153: 7718.22 | S153: 5355.93 | T153: 7718.22 | U153: 2362.29 | V153: 0.30606668 | W153: 0 | X153: June | Y153: 2024 | Z153: Pending | AA153: Returned | AB153: Yes | AC153: No | AD153: No | AE153: No | AF153: No | AG153: No | AH153: No | AI153: Warning | AJ153: 27 Jun 2024 | AK153: 06/27/2024 | AL153: Neha Gupta | AM153: Home Office | AO153: Madhya Pradesh | AP153: Indore | AQ153: Technology | AR153: Copiers | AS153: Standard Class | AT153: 0 | AU153: Pending | AV153: Returned
A154: ORD-2024-10153 | B154: 45457 | C154: 45460 | D154: CUST-6160 | E154: Kabir Singh | F154: Small Business | G154: South | H154: Kerala | I154: Kochi | J154: Furniture | K154: Tables | M154: Second Class | N154: 6 | O154: 1088.04 | P154: 0.1 | Q154: 0.1 | R154: 5875.42 | S154: 4380.55 | T154: 5875.416 | U154: 1494.866 | V154: 0.25442726 | W154: 3 | X154: June | Y154: 2024 | Z154: Pending | AA154: Returned | AB154: No | AC154: No | AD154: No | AE154: No | AF154: No | AG154: No | AH154: No | AI154: Clean | AJ154: 14 Jun 2024 | AK154: 06/17/2024 | AL154: Kabir Singh | AM154: Small Business | AN154: South | AO154: Kerala | AP154: Kochi | AQ154: Furniture | AR154: Tables | AS154: Second Class | AT154: 0.1 | AU154: Pending | AV154: Returned
A155: ORD-2025-10154 | B155: 45923 | C155: 45925 | D155: CUST-6971 | E155: Aditi Sen | F155: Consumer | G155: East | H155: Odisha | I155: Bhubaneswar | J155: Office Supplies | K155: Labels | M155: Standard Class | N155: 7 | O155: 3280.31 | P155: 0 | Q155: 0 | R155: 22962.17 | S155: 15716.5 | T155: 22962.17 | U155: 7245.67 | V155: 0.31554814 | W155: 2 | X155: September | Y155: 2025 | Z155: Refunded | AA155: Returned | AB155: No | AC155: No | AD155: No | AE155: No | AF155: No | AG155: No | AH155: No | AI155: Clean | AJ155: 23 Sep 2025 | AK155: 2025-09-25 | AL155: Aditi Sen | AM155: Consumer | AN155: East | AO155: Odisha | AP155: Bhubaneswar | AQ155: Office Supplies | AR155: Labels | AS155: Standard Class | AT155: 0 | AU155: Refunded | AV155: Returned
A156: ORD-2024-10155 | B156: 45334 | C156: 45333 | D156: CUST-7764 | E156: Priya Menon | F156: Consumer | G156: South | H156: Tamil Nadu | I156: Chennai | J156: Furniture | K156: Bookcases | M156: Same Day | N156: 1 | O156: 2599.12 | P156: 0.15 | Q156: 0.15 | R156: 2209.25 | S156: 1523.78 | T156: 2209.252 | U156: 685.472 | V156: 0.31027334 | W156: -1 | X156: February | Y156: 2024 | Z156: Paid | AA156: Completed | AB156: No | AC156: No | AD156: No | AE156: Yes | AF156: No | AG156: No | AH156: Yes | AI156: Invalid | AJ156: 12 Feb 2024 | AK156: 02/11/2024 | AL156: Priya Menon | AM156: Consumer | AN156: South | AO156: Tamil Nadu | AP156: Chennai | AQ156: Furniture | AR156: Bookcases | AS156: Same Day | AT156: 0.15 | AU156: Paid | AV156: Completed
A157: ORD-2025-10156 | B157: 45683 | C157: 45691 | D157: CUST-8327 | E157: Karan Malhotra | F157: Corporate | G157: West | H157: Rajasthan | I157: Udaipur | J157: Furniture | K157: Furnishings | M157: Same Day | N157: 3 | O157: 2859.32 | P157: 0.1 | Q157: 0.1 | R157: 7720.16 | S157: 5881 | T157: 7720.164 | U157: 1839.164 | V157: 0.23822862 | W157: 8 | X157: January | Y157: 2025 | Z157: Refunded | AA157: Returned | AB157: No | AC157: No | AD157: No | AE157: No | AF157: No | AG157: No | AH157: No | AI157: Clean | AJ157: 01/26/2025 | AK157: 03 Feb 2025 | AL157: Karan Malhotra | AM157: Corporate | AN157: West | AO157: Rajasthan | AP157: Udaipur | AQ157: Furniture | AR157: Furnishings | AS157: Same Day | AT157: 0.1 | AU157: Refunded | AV157: Returned
A158: ORD-2025-10157 | B158: 45743 | C158: 45743 | D158: CUST-4058 | E158: Vikram Iyer | F158: Small Business | G158: East | H158: Bihar | I158: Patna | J158: Technology | K158: Machines | M158: Second Class | N158: 7 | O158: 2305.37 | P158: 0.25 | Q158: 0.25 | R158: 12103.19 | S158: 6717.87 | T158: 12103.192 | U158: 5385.3225 | V158: 0.44495058 | W158: 0 | X158: March | Y158: 2025 | Z158: Paid | AA158: Completed | AB158: No | AC158: No | AD158: No | AE158: No | AF158: No | AG158: No | AH158: Yes | AI158: Clean | AJ158: 27-03-2025 | AK158: 27 Mar 2025 | AL158: Vikram Iyer | AM158: Small Business | AN158: East | AO158: Bihar | AP158: Patna | AQ158: Technology | AR158: Machines | AS158: Second Class | AT158: 0.25 | AU158: Paid | AV158: Completed
...
